[
    {
        "src": "エリア",
        "dst": "区域",
        "rm": "游戏中的场景地图单位"
    },
    {
        "src": "リージョン",
        "dst": "地区",
        "rm": "多个区域构成地区"
    },
    {
        "src": "ギルド",
        "dst": "行会",
        "rm": "工匠、采集者所属的组织"
    },
    {
        "src": "バザー",
        "dst": "摆摊",
        "rm": "动词时用，玩家摆摊"
    },
    {
        "src": "パーティ",
        "dst": "小队",
        "rm": ""
    },
    {
        "src": "フレンド",
        "dst": "好友",
        "rm": ""
    },
    {
        "src": "FINAL FANTASY XI",
        "dst": "最终幻想XI",
        "rm": ""
    },
    {
        "src": "プレイオンライン",
        "dst": "易玩通",
        "rm": ""
    },
    {
        "src": "ハンドル",
        "dst": "柄角色",
        "rm": "易玩通上的账号单位，一个柄角色下绑定多个角色"
    },
    {
        "src": "マジックバースト",
        "dst": "魔法爆发",
        "rm": "游戏系统"
    },
    {
        "src": "レジストハック",
        "dst": "抗性破坏",
        "rm": "游戏系统"
    },
    {
        "src": "モグハウス",
        "dst": "莫古房屋",
        "rm": "房屋系统"
    },
    {
        "src": "フェイス",
        "dst": "亲信战友",
        "rm": "一种魔法，也指此类魔法召唤出的NPC战友"
    },
    {
        "src": "ギル",
        "dst": "金币",
        "rm": "货币单位"
    },
    {
        "src": "アライアンス",
        "dst": "团队",
        "rm": "3个小队组成团队"
    },
    {
        "src": "チョコボ",
        "dst": "陆行鸟",
        "rm": "一种动物"
    },
    {
        "src": "ダルメル",
        "dst": "长颈驼",
        "rm": "一种动物"
    },
    {
        "src": "プギル",
        "dst": "陆鱼",
        "rm": "一种动物"
    },
    {
        "src": "リーチ",
        "dst": "水蛭",
        "rm": "一种动物"
    },
    {
        "src": "エフト",
        "dst": "水蜥",
        "rm": "一种动物"
    },
    {
        "src": "エフェクト",
        "dst": "特效",
        "rm": "游戏系统演出表现所用的视觉效果"
    },
    {
        "src": "エフェクト",
        "dst": "效果",
        "rm": "战斗时附加的BUFF/DEBUFF"
    },
    {
        "src": "ロビーサーバー",
        "dst": "大厅服务器",
        "rm": ""
    },
    {
        "src": "サンドリア",
        "dst": "桑多利亚",
        "rm": "国家名"
    },
    {
        "src": "バストゥーク",
        "dst": "巴斯图克",
        "rm": "国家名"
    },
    {
        "src": "ウィンダス",
        "dst": "温达斯",
        "rm": "国家名"
    },
    {
        "src": "ジュノ",
        "dst": "朱诺",
        "rm": "国家名"
    },
    {
        "src": "オファーリスト",
        "dst": "已接受列表",
        "rm": ""
    },
    {
        "src": "コンプリートリスト",
        "dst": "已完成列表",
        "rm": ""
    },
    {
        "src": "エミネンス・レコード",
        "dst": "名望记录",
        "rm": ""
    },
    {
        "src": "エミネンス",
        "dst": "名望",
        "rm": "名望记录中获取的点数"
    },
    {
        "src": "ユニティ",
        "dst": "联合会",
        "rm": "玩家加入的一个自由组织，发行各种任务"
    },
    {
        "src": "リンクシェル",
        "dst": "通讯贝",
        "rm": "通讯工具，母机，产出通讯珠"
    },
    {
        "src": "リンクパール",
        "dst": "通讯珠",
        "rm": "通讯工具，子机"
    },
    {
        "src": "青魔法",
        "dst": "青魔法",
        "rm": "一类魔法"
    },
    {
        "src": "赤魔法",
        "dst": "赤魔法",
        "rm": "一类魔法"
    },
    {
        "src": "黒魔法",
        "dst": "黑魔法",
        "rm": "一类魔法"
    },
    {
        "src": "白魔法",
        "dst": "白魔法",
        "rm": "一类魔法"
    },
    {
        "src": "宅配サービス",
        "dst": "送货服务",
        "rm": ""
    },
    {
        "src": "感情表現",
        "dst": "情感动作",
        "rm": "有角色动画演出的表达手法"
    },
    {
        "src": "アビリティ",
        "dst": "能力",
        "rm": "一种技能"
    },
    {
        "src": "せいとん",
        "dst": "整理",
        "rm": "整理物品的动作"
    },
    {
        "src": "白魔道士",
        "dst": "白魔法师",
        "rm": ""
    },
    {
        "src": "黒魔道士",
        "dst": "黑魔法师",
        "rm": ""
    },
    {
        "src": "青魔道士",
        "dst": "青魔法师",
        "rm": ""
    },
    {
        "src": "赤魔道士",
        "dst": "赤魔法师",
        "rm": ""
    },
    {
        "src": "ヒューム",
        "dst": "休姆",
        "rm": "种族之一，人类"
    },
    {
        "src": "エルヴァーン",
        "dst": "埃尔凡",
        "rm": "种族之一，尖耳，身形修长"
    },
    {
        "src": "タルタル",
        "dst": "塔鲁塔鲁",
        "rm": "种族之一，矮小如孩童"
    },
    {
        "src": "ミスラ",
        "dst": "米斯拉",
        "rm": "种族之一，猫耳猫尾"
    },
    {
        "src": "ガルカ",
        "dst": "伽尔卡",
        "rm": "种族之一，体形魁梧"
    },
    {
        "src": "頭",
        "dst": "头",
        "rm": "装备位"
    },
    {
        "src": "胴",
        "dst": "体",
        "rm": "装备位"
    },
    {
        "src": "背",
        "dst": "背",
        "rm": "装备位"
    },
    {
        "src": "メインウェポン",
        "dst": "主武器",
        "rm": "装备位"
    },
    {
        "src": "サブウェポン",
        "dst": "副武器",
        "rm": "装备位"
    },
    {
        "src": "首",
        "dst": "颈",
        "rm": "装备位"
    },
    {
        "src": "両手",
        "dst": "手",
        "rm": "装备位"
    },
    {
        "src": "腰",
        "dst": "腰",
        "rm": "装备位"
    },
    {
        "src": "レンジウェポン",
        "dst": "远程武器",
        "rm": "装备位"
    },
    {
        "src": "左耳",
        "dst": "左耳",
        "rm": "装备位"
    },
    {
        "src": "右耳",
        "dst": "右耳",
        "rm": "装备位"
    },
    {
        "src": "左手の指",
        "dst": "左手指",
        "rm": "装备位"
    },
    {
        "src": "右手の指",
        "dst": "右手指",
        "rm": "装备位"
    },
    {
        "src": "両脚",
        "dst": "腿",
        "rm": "装备位"
    },
    {
        "src": "両足",
        "dst": "足",
        "rm": "装备位"
    },
    {
        "src": "ジョブ",
        "dst": "职业",
        "rm": "玩家的职业"
    },
    {
        "src": "リーダー",
        "dst": "队长",
        "rm": "小队队长"
    },
    {
        "src": "召喚士",
        "dst": "召唤师",
        "rm": "职业之一"
    },
    {
        "src": "モンク",
        "dst": "武僧",
        "rm": "职业之一"
    },
    {
        "src": "シーフ",
        "dst": "盗贼",
        "rm": "职业之一"
    },
    {
        "src": "獣使い",
        "dst": "驯兽师",
        "rm": "职业之一"
    },
    {
        "src": "暗黒騎士",
        "dst": "暗黑骑士",
        "rm": "职业之一"
    },
    {
        "src": "ナイト",
        "dst": "骑士",
        "rm": "职业之一"
    },
    {
        "src": "侍",
        "dst": "武士",
        "rm": "职业之一"
    },
    {
        "src": "歌の呪譜",
        "dst": "歌的咒谱",
        "rm": "习得咒歌用的乐谱"
    },
    {
        "src": "呪歌",
        "dst": "咒歌",
        "rm": "吟游诗人的歌"
    },
    {
        "src": "短剣",
        "dst": "匕首",
        "rm": "武器之一"
    },
    {
        "src": "ウェポンスキル",
        "dst": "战技",
        "rm": "技能类型"
    },
    {
        "src": "フェロー",
        "dst": "搭档",
        "rm": "NPC队友"
    },
    {
        "src": "シャットダウン",
        "dst": "退出游戏",
        "rm": "游戏系统指令"
    },
    {
        "src": "ログイン",
        "dst": "登入",
        "rm": ""
    },
    {
        "src": "ログアウト",
        "dst": "登出",
        "rm": ""
    },
    {
        "src": "リクエスト",
        "dst": "请求",
        "rm": "游戏内向其他玩家发出的请求"
    },
    {
        "src": "クエスト",
        "dst": "委托",
        "rm": "支线任务"
    },
    {
        "src": "ミュートリスト",
        "dst": "屏蔽列表",
        "rm": ""
    },
    {
        "src": "ザンネン",
        "dst": "踩",
        "rm": "评价"
    },
    {
        "src": "イイネ！",
        "dst": "赞",
        "rm": "评价"
    },
    {
        "src": "モグワードローブ",
        "dst": "莫古衣柜",
        "rm": ""
    },
    {
        "src": "モグ金庫",
        "dst": "莫古金库",
        "rm": ""
    },
    {
        "src": "マイバッグ",
        "dst": "背包",
        "rm": ""
    },
    {
        "src": "モグサッチェル",
        "dst": "莫古手提包",
        "rm": ""
    },
    {
        "src": "モグサック",
        "dst": "莫古行囊",
        "rm": ""
    },
    {
        "src": "モグケース",
        "dst": "莫古手提箱",
        "rm": ""
    },
    {
        "src": "メインジョブ",
        "dst": "主职业",
        "rm": ""
    },
    {
        "src": "サポートジョブ",
        "dst": "副职业",
        "rm": ""
    },
    {
        "src": "プロマシアの呪縛",
        "dst": "普罗玛西亚的咒缚",
        "rm": "扩展包之一"
    },
    {
        "src": "プロマシア",
        "dst": "普罗玛西亚",
        "rm": "神名"
    },
    {
        "src": "アトルガンの秘宝",
        "dst": "阿图尔冈的秘宝",
        "rm": "扩张包之一"
    },
    {
        "src": "アトルガン",
        "dst": "阿图尔冈",
        "rm": "地名"
    },
    {
        "src": "アルタナの神兵",
        "dst": "阿尔塔娜的神兵",
        "rm": "扩展包之一"
    },
    {
        "src": "アルタナ",
        "dst": "阿尔塔娜",
        "rm": "神名"
    },
    {
        "src": "石の見る夢",
        "dst": "石之梦",
        "rm": "额外任务"
    },
    {
        "src": "戦慄！モグ祭りの夜",
        "dst": "战栗！莫古祭之夜",
        "rm": "额外任务"
    },
    {
        "src": "シャントット帝国の陰謀",
        "dst": "香托托帝国的阴谋",
        "rm": "额外任务"
    },
    {
        "src": "アビセア",
        "dst": "阿比塞亚",
        "rm": "地名"
    },
    {
        "src": "アドゥリンの魔境",
        "dst": "阿杜林的魔境",
        "rm": "扩展包之一"
    },
    {
        "src": "アドゥリン",
        "dst": "阿杜林",
        "rm": "地名"
    },
    {
        "src": "コロナイズ",
        "dst": "殖民",
        "rm": "玩法"
    },
    {
        "src": "ワークス",
        "dst": "行动",
        "rm": "联合军命令"
    },
    {
        "src": "ヴァナ・ディールの星唄",
        "dst": "瓦纳·迪尔的星歌",
        "rm": "额外任务"
    },
    {
        "src": "ヴァナ・ディール",
        "dst": "瓦纳·迪尔",
        "rm": "地名，世界，故事的舞台"
    },
    {
        "src": "蝕世のエンブリオ",
        "dst": "蚀世的胚卵",
        "rm": "额外任务"
    },
    {
        "src": "ジラートの幻影",
        "dst": "吉拉特的幻影",
        "rm": "扩展包之一"
    },
    {
        "src": "ジラート",
        "dst": "吉拉特",
        "rm": "古国名"
    },
    {
        "src": "クリュー",
        "dst": "克琉",
        "rm": "古族名"
    },
    {
        "src": "コンクェスト",
        "dst": "征战",
        "rm": "玩法"
    },
    {
        "src": "カンパニエ",
        "dst": "联军",
        "rm": "玩法"
    },
    {
        "src": "ビシージ",
        "dst": "攻城",
        "rm": "玩法"
    },
    {
        "src": "ミッション",
        "dst": "任务",
        "rm": "主线任务"
    },
    {
        "src": "片手剣",
        "dst": "单手剑",
        "rm": "武器种类"
    },
    {
        "src": "片手棍",
        "dst": "单手杖",
        "rm": "武器种类"
    },
    {
        "src": "両手棍",
        "dst": "双手杖",
        "rm": "武器种类"
    },
    {
        "src": "風水鈴",
        "dst": "风水铃",
        "rm": "武器种类"
    },
    {
        "src": "アトリビュート",
        "dst": "特性",
        "rm": "被动技能"
    },
    {
        "src": "ペトラ",
        "dst": "佩特拉",
        "rm": "一种特殊道具"
    },
    {
        "src": "タブ",
        "dst": "塔布",
        "rm": "一种点数"
    },
    {
        "src": "オートマトン",
        "dst": "自走人偶",
        "rm": "人偶师的宠物"
    },
    {
        "src": "ペット",
        "dst": "宠物",
        "rm": "召唤师的宠物，亦指所有召唤物"
    },
    {
        "src": "漁師",
        "dst": "渔夫",
        "rm": "作为行会名时"
    },
    {
        "src": "木工",
        "dst": "木匠",
        "rm": "作为行会名时"
    },
    {
        "src": "鍛冶",
        "dst": "铁匠",
        "rm": "作为行会名时"
    },
    {
        "src": "彫金",
        "dst": "金匠",
        "rm": "作为行会名时"
    },
    {
        "src": "織工",
        "dst": "裁缝",
        "rm": "作为行会名时"
    },
    {
        "src": "革工",
        "dst": "皮匠",
        "rm": "作为行会名时"
    },
    {
        "src": "骨工",
        "dst": "骨匠",
        "rm": "作为行会名时"
    },
    {
        "src": "錬金術",
        "dst": "炼金术",
        "rm": "作为行会名时"
    },
    {
        "src": "調理",
        "dst": "厨师",
        "rm": "作为行会名时"
    },
    {
        "src": "ロール",
        "dst": "骰",
        "rm": "一种道具，是骰子，根据职业有不同的种类"
    },
    {
        "src": "テラー",
        "dst": "恐惧",
        "rm": "状态"
    },
    {
        "src": "スタン",
        "dst": "眩晕",
        "rm": "黑魔法"
    },
    {
        "src": "バインド",
        "dst": "止步",
        "rm": "黑魔法"
    },
    {
        "src": "ヘヴィ",
        "dst": "加重",
        "rm": "状态"
    },
    {
        "src": "スロウ",
        "dst": "减速",
        "rm": "白魔法"
    },
    {
        "src": "受け流し",
        "dst": "招架",
        "rm": ""
    },
    {
        "src": "モグロッカー",
        "dst": "莫古储物柜",
        "rm": ""
    },
    {
        "src": "落札",
        "dst": "落槌",
        "rm": "拍卖术语"
    },
    {
        "src": "入札",
        "dst": "出价",
        "rm": "拍卖术语"
    },
    {
        "src": "出品",
        "dst": "寄售",
        "rm": "拍卖术语"
    },
    {
        "src": "競売所",
        "dst": "拍卖行",
        "rm": "游戏系统，设施"
    },
    {
        "src": "からくり士",
        "dst": "机关师",
        "rm": "职业"
    },
    {
        "src": "コンボ",
        "dst": "连击",
        "rm": "战技名"
    },
    {
        "src": "タックル",
        "dst": "冲撞",
        "rm": "战技名"
    },
    {
        "src": "短勁",
        "dst": "短劲",
        "rm": "战技名"
    },
    {
        "src": "バックハンドブロー",
        "dst": "翻背拳",
        "rm": "战技名"
    },
    {
        "src": "乱撃",
        "dst": "乱击",
        "rm": "战技名"
    },
    {
        "src": "スピンアタック",
        "dst": "回旋打击",
        "rm": "战技名"
    },
    {
        "src": "空鳴拳",
        "dst": "空鸣拳",
        "rm": "战技名"
    },
    {
        "src": "双竜脚",
        "dst": "双龙脚",
        "rm": "战技名"
    },
    {
        "src": "夢想阿修羅拳",
        "dst": "梦想阿修罗拳",
        "rm": "战技名"
    },
    {
        "src": "闘魂旋風脚",
        "dst": "斗魂旋风脚",
        "rm": "战技名"
    },
    {
        "src": "ファイナルパラダイス",
        "dst": "最终乐园",
        "rm": "战技名"
    },
    {
        "src": "ファイナルヘヴン",
        "dst": "最终天堂",
        "rm": "战技名"
    },
    {
        "src": "アスケーテンツォルン",
        "dst": "苦行僧之怒",
        "rm": "战技名"
    },
    {
        "src": "連環六合圏",
        "dst": "连环六合圈",
        "rm": "战技名"
    },
    {
        "src": "ビクトリースマイト",
        "dst": "必胜重击",
        "rm": "战技名"
    },
    {
        "src": "四神円舞",
        "dst": "四神圆舞",
        "rm": "战技名"
    },
    {
        "src": "ドラゴンブロウ",
        "dst": "飞龙拳",
        "rm": "战技名"
    },
    {
        "src": "マルカラ",
        "dst": "秘穴拳",
        "rm": "战技名"
    },
    {
        "src": "ワスプスティング",
        "dst": "蜂针",
        "rm": "战技名"
    },
    {
        "src": "ガストスラッシュ",
        "dst": "突风斩",
        "rm": "战技名"
    },
    {
        "src": "シャドーステッチ",
        "dst": "缠影刃",
        "rm": "战技名"
    },
    {
        "src": "バイパーバイト",
        "dst": "蛇牙",
        "rm": "战技名"
    },
    {
        "src": "サイクロン",
        "dst": "气旋",
        "rm": "战技名"
    },
    {
        "src": "エナジースティール",
        "dst": "能量偷取",
        "rm": "战技名"
    },
    {
        "src": "エナジードレイン",
        "dst": "能量吸收",
        "rm": "战技名"
    },
    {
        "src": "ダンシングエッジ",
        "dst": "飞舞刃",
        "rm": "战技名"
    },
    {
        "src": "シャークバイト",
        "dst": "鲛噬",
        "rm": "战技名"
    },
    {
        "src": "エヴィサレーション",
        "dst": "剜心刺",
        "rm": "战技名"
    },
    {
        "src": "イオリアンエッジ",
        "dst": "狂风刃",
        "rm": "战技名"
    },
    {
        "src": "マーシーストローク",
        "dst": "慈悲杀",
        "rm": "战技名"
    },
    {
        "src": "マンダリクスタッブ",
        "dst": "曼荼罗杀",
        "rm": "战技名"
    },
    {
        "src": "モーダントライム",
        "dst": "冷霜",
        "rm": "战技名"
    },
    {
        "src": "ピリッククレオス",
        "dst": "血染胜利",
        "rm": "战技名"
    },
    {
        "src": "ルドラストーム",
        "dst": "狂风骤雨",
        "rm": "战技名"
    },
    {
        "src": "エクゼンテレター",
        "dst": "削骨刺",
        "rm": "战技名"
    },
    {
        "src": "ルースレスストローク",
        "dst": "无情杀",
        "rm": "战技名"
    },
    {
        "src": "ファストブレード",
        "dst": "先锋剑",
        "rm": "战技名"
    },
    {
        "src": "バーニングブレード",
        "dst": "燃烧剑",
        "rm": "战技名"
    },
    {
        "src": "レッドロータス",
        "dst": "红莲剑",
        "rm": "战技名"
    },
    {
        "src": "フラットブレード",
        "dst": "横扫剑",
        "rm": "战技名"
    },
    {
        "src": "シャインブレード",
        "dst": "光明之刃",
        "rm": "战技名"
    },
    {
        "src": "セラフブレード",
        "dst": "炽天使刃",
        "rm": "战技名"
    },
    {
        "src": "サークルブレード",
        "dst": "回旋斩",
        "rm": "战技名"
    },
    {
        "src": "スピリッツウィズイン",
        "dst": "深奥之灵",
        "rm": "战技名"
    },
    {
        "src": "ボーパルブレード",
        "dst": "致命斩",
        "rm": "战技名"
    },
    {
        "src": "スウィフトブレード",
        "dst": "迅捷剑",
        "rm": "战技名"
    },
    {
        "src": "サベッジブレード",
        "dst": "狂怒剑",
        "rm": "战技名"
    },
    {
        "src": "サンギンブレード",
        "dst": "嗜血刃",
        "rm": "战技名"
    },
    {
        "src": "ナイスオブラウンド",
        "dst": "圆硕骑士",
        "rm": "战技名"
    },
    {
        "src": "ナイツオブラウンド",
        "dst": "圆桌骑士",
        "rm": "战技名"
    },
    {
        "src": "ロズレーファタール",
        "dst": "致命玫瑰",
        "rm": "战技名"
    },
    {
        "src": "ロイエ",
        "dst": "赎罪剑",
        "rm": "战技名"
    },
    {
        "src": "エクスピアシオン",
        "dst": "偿赎剑",
        "rm": "战技名"
    },
    {
        "src": "ウリエルブレード",
        "dst": "大天使刃",
        "rm": "战技名"
    },
    {
        "src": "グローリースラッシュ",
        "dst": "荣耀斩",
        "rm": "战技名"
    },
    {
        "src": "シャンデュシニュ",
        "dst": "白鸟之歌",
        "rm": "战技名"
    },
    {
        "src": "レクイエスカット",
        "dst": "安魂祈祷",
        "rm": "战技名"
    },
    {
        "src": "ファストブレードII",
        "dst": "先锋剑II",
        "rm": "战技名"
    },
    {
        "src": "インペラトル",
        "dst": "绝对统治",
        "rm": "战技名"
    },
    {
        "src": "ハードスラッシュ",
        "dst": "重斩",
        "rm": "战技名"
    },
    {
        "src": "パワースラッシュ",
        "dst": "强力斩",
        "rm": "战技名"
    },
    {
        "src": "フロストバイト",
        "dst": "寒冰剑",
        "rm": "战技名"
    },
    {
        "src": "フリーズバイト",
        "dst": "冻结剑",
        "rm": "战技名"
    },
    {
        "src": "ショックウェーブ",
        "dst": "震荡波",
        "rm": "战技名"
    },
    {
        "src": "クレセントムーン",
        "dst": "新月斩",
        "rm": "战技名"
    },
    {
        "src": "シックルムーン",
        "dst": "弦月斩",
        "rm": "战技名"
    },
    {
        "src": "スピンスラッシュ",
        "dst": "回环斩",
        "rm": "战技名"
    },
    {
        "src": "グラウンドストライク",
        "dst": "地面冲击",
        "rm": "战技名"
    },
    {
        "src": "ヘラクレススラッシュ",
        "dst": "力神斩",
        "rm": "战技名"
    },
    {
        "src": "スカージ",
        "dst": "灾变",
        "rm": "战技名"
    },
    {
        "src": "トアクリーバー",
        "dst": "切削",
        "rm": "战技名"
    },
    {
        "src": "レゾルーション",
        "dst": "决断",
        "rm": "战技名"
    },
    {
        "src": "デミディエーション",
        "dst": "一刀两断",
        "rm": "战技名"
    },
    {
        "src": "フィンブルヴェト",
        "dst": "昏兆",
        "rm": "战技名"
    },
    {
        "src": "レイジングアクス",
        "dst": "暴怒斧",
        "rm": "战技名"
    },
    {
        "src": "スマッシュ",
        "dst": "碎击",
        "rm": "战技名"
    },
    {
        "src": "ラファールアクス",
        "dst": "强风斧",
        "rm": "战技名"
    },
    {
        "src": "アバランチアクス",
        "dst": "山崩斧",
        "rm": "战技名"
    },
    {
        "src": "スピニングアクス",
        "dst": "回旋斧",
        "rm": "战技名"
    },
    {
        "src": "ランページ",
        "dst": "暴怒",
        "rm": "战技名"
    },
    {
        "src": "カラミティ",
        "dst": "灾难",
        "rm": "战技名"
    },
    {
        "src": "ミストラルアクス",
        "dst": "凛风斧",
        "rm": "战技名"
    },
    {
        "src": "デシメーション",
        "dst": "地毁人亡",
        "rm": "战技名"
    },
    {
        "src": "ボーラアクス",
        "dst": "寒风斧",
        "rm": "战技名"
    },
    {
        "src": "オンスロート",
        "dst": "猛攻",
        "rm": "战技名"
    },
    {
        "src": "プライマルレンド",
        "dst": "蛮荒崩裂",
        "rm": "战技名"
    },
    {
        "src": "クラウドスプリッタ",
        "dst": "云层破斩",
        "rm": "战技名"
    },
    {
        "src": "ルイネーター",
        "dst": "毁灭斩",
        "rm": "战技名"
    },
    {
        "src": "ブリッツ",
        "dst": "闪电斩",
        "rm": "战技名"
    },
    {
        "src": "シールドブレイク",
        "dst": "破坏盾牌",
        "rm": "战技名"
    },
    {
        "src": "アイアンテンペスト",
        "dst": "锐铁暴风",
        "rm": "战技名"
    },
    {
        "src": "シュトルムヴィント",
        "dst": "暴风斩",
        "rm": "战技名"
    },
    {
        "src": "アーマーブレイク",
        "dst": "破甲",
        "rm": "战技名"
    },
    {
        "src": "キーンエッジ",
        "dst": "利刃斩",
        "rm": "战技名"
    },
    {
        "src": "ウェポンブレイク",
        "dst": "武装解除",
        "rm": "战技名"
    },
    {
        "src": "レイジングラッシュ",
        "dst": "裂石暴环",
        "rm": "战技名"
    },
    {
        "src": "フルブレイク",
        "dst": "全部破坏",
        "rm": "战技名"
    },
    {
        "src": "スチールサイクロン",
        "dst": "钢铁旋风",
        "rm": "战技名"
    },
    {
        "src": "フェルクリーヴ",
        "dst": "裂石飞环",
        "rm": "战技名"
    },
    {
        "src": "メタトロントーメント",
        "dst": "串刺天使",
        "rm": "战技名"
    },
    {
        "src": "キングズジャスティス",
        "dst": "王之正义",
        "rm": "战技名"
    },
    {
        "src": "ウッコフューリー",
        "dst": "雷神之怒",
        "rm": "战技名"
    },
    {
        "src": "アップヒーバル",
        "dst": "动乱",
        "rm": "战技名"
    },
    {
        "src": "ディザスター",
        "dst": "灾祸",
        "rm": "战技名"
    },
    {
        "src": "スライス",
        "dst": "切割",
        "rm": "战技名"
    },
    {
        "src": "ダークハーベスト",
        "dst": "黑暗收割",
        "rm": "战技名"
    },
    {
        "src": "シャドーオブデス",
        "dst": "死亡之影",
        "rm": "战技名"
    },
    {
        "src": "ナイトメアサイス",
        "dst": "噩梦钐割",
        "rm": "战技名"
    },
    {
        "src": "スピニングサイス",
        "dst": "旋转钐割",
        "rm": "战技名"
    },
    {
        "src": "ボーパルサイス",
        "dst": "斩首钐割",
        "rm": "战技名"
    },
    {
        "src": "ギロティン",
        "dst": "断首",
        "rm": "战技名"
    },
    {
        "src": "クロスリーパー",
        "dst": "交错收割",
        "rm": "战技名"
    },
    {
        "src": "スパイラルヘル",
        "dst": "螺旋地狱",
        "rm": "战技名"
    },
    {
        "src": "インファナルサイズ",
        "dst": "地狱钐割",
        "rm": "战技名"
    },
    {
        "src": "カタストロフィ",
        "dst": "天灾",
        "rm": "战技名"
    },
    {
        "src": "インサージェンシー",
        "dst": "叛乱",
        "rm": "战技名"
    },
    {
        "src": "クワイタス",
        "dst": "寂灭",
        "rm": "战技名"
    },
    {
        "src": "エントロピー",
        "dst": "熵",
        "rm": "战技名"
    },
    {
        "src": "ジ・オリジン",
        "dst": "起源时刻",
        "rm": "战技名"
    },
    {
        "src": "ダブルスラスト",
        "dst": "二重刺",
        "rm": "战技名"
    },
    {
        "src": "サンダースラスト",
        "dst": "闪雷刺",
        "rm": "战技名"
    },
    {
        "src": "ライデンスラスト",
        "dst": "雷电刺",
        "rm": "战技名"
    },
    {
        "src": "足払い",
        "dst": "扫堂枪",
        "rm": "战技名"
    },
    {
        "src": "ペンタスラスト",
        "dst": "五重刺",
        "rm": "战技名"
    },
    {
        "src": "ボーパルスラスト",
        "dst": "贯通刺",
        "rm": "战技名"
    },
    {
        "src": "スキュアー",
        "dst": "枪杆击",
        "rm": "战技名"
    },
    {
        "src": "大車輪",
        "dst": "大回旋",
        "rm": "战技名"
    },
    {
        "src": "インパルスドライヴ",
        "dst": "脉冲枪",
        "rm": "战技名"
    },
    {
        "src": "ソニックスラスト",
        "dst": "音速刺",
        "rm": "战技名"
    },
    {
        "src": "ゲイルスコグル",
        "dst": "武神枪",
        "rm": "战技名"
    },
    {
        "src": "雲蒸竜変",
        "dst": "云蒸龙变",
        "rm": "战技名"
    },
    {
        "src": "カムラン",
        "dst": "卡姆兰",
        "rm": "战技名"
    },
    {
        "src": "スターダイバー",
        "dst": "坠星冲",
        "rm": "战技名"
    },
    {
        "src": "ダーマット",
        "dst": "迪卢木多",
        "rm": "战技名"
    },
    {
        "src": "臨",
        "dst": "临",
        "rm": "战技名"
    },
    {
        "src": "烈",
        "dst": "烈",
        "rm": "战技名"
    },
    {
        "src": "滴",
        "dst": "滴",
        "rm": "战技名"
    },
    {
        "src": "凍",
        "dst": "冻",
        "rm": "战技名"
    },
    {
        "src": "地",
        "dst": "地",
        "rm": "战技名"
    },
    {
        "src": "影",
        "dst": "影",
        "rm": "战技名"
    },
    {
        "src": "迅",
        "dst": "迅",
        "rm": "战技名"
    },
    {
        "src": "天",
        "dst": "天",
        "rm": "战技名"
    },
    {
        "src": "空",
        "dst": "空",
        "rm": "战技名"
    },
    {
        "src": "湧",
        "dst": "涌",
        "rm": "战技名"
    },
    {
        "src": "生者必滅",
        "dst": "生者必灭",
        "rm": "战技名"
    },
    {
        "src": "カムハブリ",
        "dst": "神葬",
        "rm": "战技名"
    },
    {
        "src": "秘",
        "dst": "秘",
        "rm": "战技名"
    },
    {
        "src": "瞬",
        "dst": "瞬",
        "rm": "战技名"
    },
    {
        "src": "是生滅法",
        "dst": "是生灭法",
        "rm": "战技名"
    },
    {
        "src": "壱之太刀・燕飛",
        "dst": "壹之太刀·燕飞",
        "rm": "战技名"
    },
    {
        "src": "弐之太刀・鋒縛",
        "dst": "贰之太刀·锋缚",
        "rm": "战技名"
    },
    {
        "src": "参之太刀・轟天",
        "dst": "叁之太刀·轰天",
        "rm": "战技名"
    },
    {
        "src": "四之太刀・陽炎",
        "dst": "肆之太刀·阳炎",
        "rm": "战技名"
    },
    {
        "src": "五之太刀・陣風",
        "dst": "伍之太刀·阵风",
        "rm": "战技名"
    },
    {
        "src": "六之太刀・光輝",
        "dst": "陆之太刀·光辉",
        "rm": "战技名"
    },
    {
        "src": "七之太刀・雪風",
        "dst": "柒之太刀·雪风",
        "rm": "战技名"
    },
    {
        "src": "八之太刀・月光",
        "dst": "捌之太刀·月光",
        "rm": "战技名"
    },
    {
        "src": "九之太刀・花車",
        "dst": "玖之太刀·花车",
        "rm": "战技名"
    },
    {
        "src": "十一之太刀・鳳蝶",
        "dst": "拾壹之太刀·凤蝶",
        "rm": "战技名"
    },
    {
        "src": "盛夏之太刀・西瓜割",
        "dst": "盛夏之太刀·西瓜割",
        "rm": "战技名"
    },
    {
        "src": "零之太刀・回天",
        "dst": "零之太刀·回天",
        "rm": "战技名"
    },
    {
        "src": "十之太刀・乱鴉",
        "dst": "拾之太刀·乱鸦",
        "rm": "战技名"
    },
    {
        "src": "祖之太刀・不動",
        "dst": "祖之太刀·不动",
        "rm": "战技名"
    },
    {
        "src": "十二之太刀・照破",
        "dst": "拾贰之太刀·照破",
        "rm": "战技名"
    },
    {
        "src": "絶之太刀・無名",
        "dst": "绝之太刀·无名",
        "rm": "战技名"
    },
    {
        "src": "シャインストライク",
        "dst": "光明强袭",
        "rm": "战技名"
    },
    {
        "src": "セラフストライク",
        "dst": "炽天强袭",
        "rm": "战技名"
    },
    {
        "src": "ブレインシェイカー",
        "dst": "震脑斩",
        "rm": "战技名"
    },
    {
        "src": "スターライト",
        "dst": "星之光",
        "rm": "战技名"
    },
    {
        "src": "ムーンライト",
        "dst": "月之光",
        "rm": "战技名"
    },
    {
        "src": "スカルブレイカー",
        "dst": "碎颅",
        "rm": "战技名"
    },
    {
        "src": "トゥルーストライク",
        "dst": "真理强袭",
        "rm": "战技名"
    },
    {
        "src": "ジャッジメント",
        "dst": "制裁",
        "rm": "战技名"
    },
    {
        "src": "ヘキサストライク",
        "dst": "六重强袭",
        "rm": "战技名"
    },
    {
        "src": "ブラックヘイロー",
        "dst": "黑色光环",
        "rm": "战技名"
    },
    {
        "src": "フラッシュノヴァ",
        "dst": "闪耀新星",
        "rm": "战技名"
    },
    {
        "src": "ランドグリース",
        "dst": "武神杖",
        "rm": "战技名"
    },
    {
        "src": "ミスティックブーン",
        "dst": "神秘恩惠",
        "rm": "战技名"
    },
    {
        "src": "ダガン",
        "dst": "破晓",
        "rm": "战技名"
    },
    {
        "src": "レルムレイザー",
        "dst": "灭境",
        "rm": "战技名"
    },
    {
        "src": "エクズデーション",
        "dst": "渗透",
        "rm": "战技名"
    },
    {
        "src": "ダグダ",
        "dst": "全能神之杖",
        "rm": "战技名"
    },
    {
        "src": "ヘヴィスイング",
        "dst": "重劈",
        "rm": "战技名"
    },
    {
        "src": "ロッククラッシャー",
        "dst": "碎岩一击",
        "rm": "战技名"
    },
    {
        "src": "アースクラッシャー",
        "dst": "裂地",
        "rm": "战技名"
    },
    {
        "src": "スターバースト",
        "dst": "星辰爆破",
        "rm": "战技名"
    },
    {
        "src": "サンバースト",
        "dst": "日轮爆破",
        "rm": "战技名"
    },
    {
        "src": "シェルクラッシャー",
        "dst": "破盾一击",
        "rm": "战技名"
    },
    {
        "src": "フルスイング",
        "dst": "全力挥打",
        "rm": "战技名"
    },
    {
        "src": "スピリットテーカー",
        "dst": "灵魂收取",
        "rm": "战技名"
    },
    {
        "src": "レトリビューション",
        "dst": "天罚",
        "rm": "战技名"
    },
    {
        "src": "カタクリスム",
        "dst": "大灾变",
        "rm": "战技名"
    },
    {
        "src": "タルタロスゲート",
        "dst": "冥狱之门",
        "rm": "战技名"
    },
    {
        "src": "ヴィゾフニル",
        "dst": "维德弗尼尔",
        "rm": "战技名"
    },
    {
        "src": "ガーランドオブブリス",
        "dst": "幸福花环",
        "rm": "战技名"
    },
    {
        "src": "オムニシエンス",
        "dst": "全知杖",
        "rm": "战技名"
    },
    {
        "src": "タルタロストーパー",
        "dst": "炼狱冬眠",
        "rm": "战技名"
    },
    {
        "src": "ミルキル",
        "dst": "至暗",
        "rm": "战技名"
    },
    {
        "src": "シャッターソウル",
        "dst": "粉碎之魂",
        "rm": "战技名"
    },
    {
        "src": "オシャラ",
        "dst": "奥巴塔拉",
        "rm": "战技名"
    },
    {
        "src": "フレイミングアロー",
        "dst": "烈火箭",
        "rm": "战技名"
    },
    {
        "src": "ピアシングアロー",
        "dst": "贯穿箭",
        "rm": "战技名"
    },
    {
        "src": "ダリングアロー",
        "dst": "消声箭",
        "rm": "战技名"
    },
    {
        "src": "サイドワインダー",
        "dst": "侧风诱导箭",
        "rm": "战技名"
    },
    {
        "src": "ブラストアロー",
        "dst": "爆破箭",
        "rm": "战技名"
    },
    {
        "src": "アーチングアロー",
        "dst": "圆弧箭",
        "rm": "战技名"
    },
    {
        "src": "エンピリアルアロー",
        "dst": "九天连箭",
        "rm": "战技名"
    },
    {
        "src": "リフルジェントアロー",
        "dst": "辉煌箭",
        "rm": "战技名"
    },
    {
        "src": "南無八幡",
        "dst": "南无八幡",
        "rm": "战技名"
    },
    {
        "src": "ジシュヌの光輝",
        "dst": "吉湿奴的光辉",
        "rm": "战技名"
    },
    {
        "src": "エイペクスアロー",
        "dst": "绝峰箭",
        "rm": "战技名"
    },
    {
        "src": "シャルヴ",
        "dst": "神射手",
        "rm": "战技名"
    },
    {
        "src": "ホットショット",
        "dst": "热弹",
        "rm": "战技名"
    },
    {
        "src": "スプリットショット",
        "dst": "分裂弹",
        "rm": "战技名"
    },
    {
        "src": "スナイパーショット",
        "dst": "狙击弹",
        "rm": "战技名"
    },
    {
        "src": "スラッグショット",
        "dst": "独头弹",
        "rm": "战技名"
    },
    {
        "src": "ブラストショット",
        "dst": "爆破射击",
        "rm": "战技名"
    },
    {
        "src": "ヘヴィショット",
        "dst": "强力射击",
        "rm": "战技名"
    },
    {
        "src": "デトネーター",
        "dst": "起爆",
        "rm": "战技名"
    },
    {
        "src": "ナビングショット",
        "dst": "迟缓弹",
        "rm": "战技名"
    },
    {
        "src": "カラナック",
        "dst": "葬歌",
        "rm": "战技名"
    },
    {
        "src": "トゥルーフライト",
        "dst": "真实射击",
        "rm": "战技名"
    },
    {
        "src": "レデンサリュート",
        "dst": "铅制礼炮",
        "rm": "战技名"
    },
    {
        "src": "ワイルドファイア",
        "dst": "野火",
        "rm": "战技名"
    },
    {
        "src": "ラストスタンド",
        "dst": "最终反抗",
        "rm": "战技名"
    },
    {
        "src": "ジ・エンド",
        "dst": "终结时刻",
        "rm": "战技名"
    },
    {
        "src": "マイティストライク",
        "dst": "强力冲击",
        "rm": "能力/特性"
    },
    {
        "src": "挑発",
        "dst": "挑衅",
        "rm": "能力/特性"
    },
    {
        "src": "物理防御力アップ",
        "dst": "物理防御力提升",
        "rm": "能力/特性"
    },
    {
        "src": "バーサク",
        "dst": "狂暴",
        "rm": "能力/特性"
    },
    {
        "src": "レジストウィルス",
        "dst": "病毒抗性",
        "rm": "能力/特性"
    },
    {
        "src": "ディフェンダー",
        "dst": "防御者",
        "rm": "能力/特性"
    },
    {
        "src": "ダブルアタック",
        "dst": "双重攻击",
        "rm": "能力/特性"
    },
    {
        "src": "物理攻撃力アップ",
        "dst": "物理攻击力提升",
        "rm": "能力/特性"
    },
    {
        "src": "HPmaxアップ",
        "dst": "体力上限提升",
        "rm": "能力/特性"
    },
    {
        "src": "スマイト",
        "dst": "猛击",
        "rm": "能力/特性"
    },
    {
        "src": "ウォークライ",
        "dst": "战嚎",
        "rm": "能力/特性"
    },
    {
        "src": "ダメージ上限アップ",
        "dst": "伤害上限提升",
        "rm": "能力/特性"
    },
    {
        "src": "アグレッサー",
        "dst": "侵攻",
        "rm": "能力/特性"
    },
    {
        "src": "フェンサー",
        "dst": "剑斗士",
        "rm": "能力/特性"
    },
    {
        "src": "リタリエーション",
        "dst": "报复",
        "rm": "能力/特性"
    },
    {
        "src": "ウォリアーチャージ",
        "dst": "战士的积攒",
        "rm": "能力/特性"
    },
    {
        "src": "トマホーク",
        "dst": "飞斧",
        "rm": "能力/特性"
    },
    {
        "src": "サベッジリ",
        "dst": "残暴",
        "rm": "能力/特性"
    },
    {
        "src": "アグレシブエイム",
        "dst": "侵掠目标",
        "rm": "能力/特性"
    },
    {
        "src": "リストレント",
        "dst": "抑制",
        "rm": "能力/特性"
    },
    {
        "src": "C.インクリース",
        "dst": "暴击伤害提升",
        "rm": "能力/特性"
    },
    {
        "src": "シールドマスタリー",
        "dst": "盾牌精通",
        "rm": "能力/特性"
    },
    {
        "src": "エクストリームガード",
        "dst": "极致防御",
        "rm": "能力/特性"
    },
    {
        "src": "ブラッドレイジ",
        "dst": "血怒",
        "rm": "能力/特性"
    },
    {
        "src": "ブラーゼンラッシュ",
        "dst": "铁壁奇袭",
        "rm": "能力/特性"
    },
    {
        "src": "百烈拳",
        "dst": "百烈拳",
        "rm": "能力/特性"
    },
    {
        "src": "ためる",
        "dst": "蓄力",
        "rm": "能力/特性"
    },
    {
        "src": "カウンター",
        "dst": "反攻",
        "rm": "能力/特性"
    },
    {
        "src": "回避",
        "dst": "回避",
        "rm": "能力/特性"
    },
    {
        "src": "チャクラ",
        "dst": "脉轮",
        "rm": "能力/特性"
    },
    {
        "src": "発剄",
        "dst": "发劲",
        "rm": "能力/特性"
    },
    {
        "src": "女神の祝福",
        "dst": "女神的祝福",
        "rm": "能力/特性"
    },
    {
        "src": "女神の印",
        "dst": "女神的印记",
        "rm": "能力/特性"
    },
    {
        "src": "ハートオブソラス",
        "dst": "安慰之心",
        "rm": "能力/特性"
    },
    {
        "src": "ハートオブミゼリ",
        "dst": "苦难之心",
        "rm": "能力/特性"
    },
    {
        "src": "女神の慈悲",
        "dst": "女神的慈悲",
        "rm": "能力/特性"
    },
    {
        "src": "魔法防御力アップ",
        "dst": "魔法防御力提升",
        "rm": "能力/特性"
    },
    {
        "src": "女神の愛撫",
        "dst": "女神的爱抚",
        "rm": "能力/特性"
    },
    {
        "src": "女神の聖域",
        "dst": "女神的圣域",
        "rm": "能力/特性"
    },
    {
        "src": "女神の羽衣",
        "dst": "女神的羽衣",
        "rm": "能力/特性"
    },
    {
        "src": "連続魔",
        "dst": "连续咏唱",
        "rm": "能力/特性"
    },
    {
        "src": "ファストキャスト",
        "dst": "神速咏唱",
        "rm": "能力/特性"
    },
    {
        "src": "絶対回避",
        "dst": "绝对回避",
        "rm": "能力/特性"
    },
    {
        "src": "ぬすむ",
        "dst": "偷盗",
        "rm": "能力/特性"
    },
    {
        "src": "ギルスティール",
        "dst": "金币窃贼",
        "rm": "能力/特性"
    },
    {
        "src": "物理回避率アップ",
        "dst": "物理回避率提升",
        "rm": "能力/特性"
    },
    {
        "src": "不意打ち",
        "dst": "出其不意",
        "rm": "能力/特性"
    },
    {
        "src": "トレジャーハンター",
        "dst": "秘宝猎人",
        "rm": "能力/特性"
    },
    {
        "src": "レジストグラビティ",
        "dst": "加重抗性",
        "rm": "能力/特性"
    },
    {
        "src": "とんずら",
        "dst": "遁逃",
        "rm": "能力/特性"
    },
    {
        "src": "だまし討ち",
        "dst": "攻其不备",
        "rm": "能力/特性"
    },
    {
        "src": "かすめとる",
        "dst": "豪夺",
        "rm": "能力/特性"
    },
    {
        "src": "トレジャーハンターII",
        "dst": "秘宝猎人II",
        "rm": "能力/特性"
    },
    {
        "src": "かくれる",
        "dst": "隐遁",
        "rm": "能力/特性"
    },
    {
        "src": "トリプルアタック",
        "dst": "三重攻击",
        "rm": "能力/特性"
    },
    {
        "src": "アサシン",
        "dst": "暗杀者",
        "rm": "能力/特性"
    },
    {
        "src": "アカンプリス",
        "dst": "共犯",
        "rm": "能力/特性"
    },
    {
        "src": "コラボレーター",
        "dst": "协力者",
        "rm": "能力/特性"
    },
    {
        "src": "フェイント",
        "dst": "虚枪",
        "rm": "能力/特性"
    },
    {
        "src": "トレジャーハンターIII",
        "dst": "秘宝猎人III",
        "rm": "能力/特性"
    },
    {
        "src": "二刀流",
        "dst": "二刀流",
        "rm": "能力/特性"
    },
    {
        "src": "インビンシブル",
        "dst": "神圣领域",
        "rm": "能力/特性"
    },
    {
        "src": "ホーリーサークル",
        "dst": "圣环",
        "rm": "能力/特性"
    },
    {
        "src": "シールドバッシュ",
        "dst": "盾牌猛击",
        "rm": "能力/特性"
    },
    {
        "src": "レジストスリープ",
        "dst": "睡眠抗性",
        "rm": "能力/特性"
    },
    {
        "src": "センチネル",
        "dst": "预警",
        "rm": "能力/特性"
    },
    {
        "src": "かばう",
        "dst": "保护",
        "rm": "能力/特性"
    },
    {
        "src": "アイアンウィル",
        "dst": "钢铁信念",
        "rm": "能力/特性"
    },
    {
        "src": "ガーディアン",
        "dst": "卫护",
        "rm": "能力/特性"
    },
    {
        "src": "パリセード",
        "dst": "护栏",
        "rm": "能力/特性"
    },
    {
        "src": "ブラッドウェポン",
        "dst": "血剑",
        "rm": "能力/特性"
    },
    {
        "src": "アルケインサークル",
        "dst": "神秘环",
        "rm": "能力/特性"
    },
    {
        "src": "ラストリゾート",
        "dst": "最终手段",
        "rm": "能力/特性"
    },
    {
        "src": "デスペレートブロー",
        "dst": "铤身一击",
        "rm": "能力/特性"
    },
    {
        "src": "レジストパライズ",
        "dst": "麻痹抗性",
        "rm": "能力/特性"
    },
    {
        "src": "ウェポンバッシュ",
        "dst": "武器猛击",
        "rm": "能力/特性"
    },
    {
        "src": "アルカナキラー",
        "dst": "奥秘杀手",
        "rm": "能力/特性"
    },
    {
        "src": "暗黑",
        "dst": "暗黑",
        "rm": "能力/特性"
    },
    {
        "src": "マジックアキュメン",
        "dst": "魔力敏锐",
        "rm": "能力/特性"
    },
    {
        "src": "ストルワートソウル",
        "dst": "刚魂",
        "rm": "能力/特性"
    },
    {
        "src": "コンスームマナ",
        "dst": "燃尽魔力",
        "rm": "能力/特性"
    },
    {
        "src": "ダークシール",
        "dst": "黑暗咒印",
        "rm": "能力/特性"
    },
    {
        "src": "ディアボリクアイ",
        "dst": "暗魔之眼",
        "rm": "能力/特性"
    },
    {
        "src": "ミューテッドソウル",
        "dst": "默魂",
        "rm": "能力/特性"
    },
    {
        "src": "ネザーヴォイド",
        "dst": "虚势",
        "rm": "能力/特性"
    },
    {
        "src": "アルケインクレスト",
        "dst": "神秘纹",
        "rm": "能力/特性"
    },
    {
        "src": "タクティカルパリー",
        "dst": "战术回避",
        "rm": "能力/特性"
    },
    {
        "src": "レッドデリリアム",
        "dst": "赤乱",
        "rm": "能力/特性"
    },
    {
        "src": "ソールエンスレーヴ",
        "dst": "灵魂仆从",
        "rm": "能力/特性"
    },
    {
        "src": "あやつる",
        "dst": "操纵",
        "rm": "能力/特性"
    },
    {
        "src": "レジストスロウ",
        "dst": "减速抗性",
        "rm": "能力/特性"
    },
    {
        "src": "ソウルボイス",
        "dst": "灵魂之声",
        "rm": "能力/特性"
    },
    {
        "src": "レジストサイレス",
        "dst": "沉默抗性",
        "rm": "能力/特性"
    },
    {
        "src": "イーグルアイ",
        "dst": "锐眼追击",
        "rm": "能力/特性"
    },
    {
        "src": "警戒",
        "dst": "警戒",
        "rm": "能力/特性"
    },
    {
        "src": "ラピッドショット",
        "dst": "速射",
        "rm": "能力/特性"
    },
    {
        "src": "乱れ撃ち",
        "dst": "纷乱箭",
        "rm": "能力/特性"
    },
    {
        "src": "明鏡止水",
        "dst": "明镜止水",
        "rm": "能力/特性"
    },
    {
        "src": "レジストブライン",
        "dst": "失明抗性",
        "rm": "能力/特性"
    },
    {
        "src": "心眼",
        "dst": "心眼",
        "rm": "能力/特性"
    },
    {
        "src": "残心",
        "dst": "残心",
        "rm": "能力/特性"
    },
    {
        "src": "黙想",
        "dst": "默想",
        "rm": "能力/特性"
    },
    {
        "src": "星眼",
        "dst": "星眼",
        "rm": "能力/特性"
    },
    {
        "src": "峰打ち",
        "dst": "刀背击打",
        "rm": "能力/特性"
    },
    {
        "src": "意気衝天",
        "dst": "意气冲天",
        "rm": "能力/特性"
    },
    {
        "src": "葉隠",
        "dst": "叶隐",
        "rm": "能力/特性"
    },
    {
        "src": "ステルス",
        "dst": "潜行",
        "rm": "能力/特性"
    },
    {
        "src": "レジストバインド",
        "dst": "止步抗性",
        "rm": "能力/特性"
    },
    {
        "src": "竜剣",
        "dst": "龙剑",
        "rm": "能力/特性"
    },
    {
        "src": "コールワイバーン",
        "dst": "召唤飞龙",
        "rm": "能力/特性"
    },
    {
        "src": "ジャンプ",
        "dst": "跳跃",
        "rm": "能力/特性"
    },
    {
        "src": "ハイジャンプ",
        "dst": "高跳",
        "rm": "能力/特性"
    },
    {
        "src": "スーパージャンプ",
        "dst": "超级跳跃",
        "rm": "能力/特性"
    },
    {
        "src": "オーバードライヴ",
        "dst": "超档",
        "rm": "能力/特性"
    },
    {
        "src": "剣の舞い",
        "dst": "剑舞",
        "rm": "能力/特性"
    },
    {
        "src": "扇の舞い",
        "dst": "扇舞",
        "rm": "能力/特性"
    },
    {
        "src": "連環計",
        "dst": "连环计",
        "rm": "能力/特性"
    },
    {
        "src": "戦術魔道書",
        "dst": "战术魔导书",
        "rm": "能力/特性"
    },
    {
        "src": "以逸待労の計",
        "dst": "以逸待劳之计",
        "rm": "能力/特性"
    },
    {
        "src": "天衣無縫の章",
        "dst": "天衣无缝之章",
        "rm": "能力/特性"
    },
    {
        "src": "ライブラ",
        "dst": "侦测",
        "rm": "能力/特性"
    },
    {
        "src": "魔物のレクイエム",
        "dst": "魔物的安魂曲",
        "rm": "魔法"
    },
    {
        "src": "ケアル",
        "dst": "治疗",
        "rm": "白魔法"
    },
    {
        "src": "ディア",
        "dst": "天辉",
        "rm": "白魔法"
    },
    {
        "src": "パライズ",
        "dst": "麻痹",
        "rm": "白魔法"
    },
    {
        "src": "バストン",
        "dst": "抗土",
        "rm": "白魔法"
    },
    {
        "src": "バニシュ",
        "dst": "放逐",
        "rm": "白魔法"
    },
    {
        "src": "バストンラ",
        "dst": "中抗土",
        "rm": "白魔法"
    },
    {
        "src": "オーラ",
        "dst": "斗气",
        "rm": "白魔法"
    },
    {
        "src": "ポイゾナ",
        "dst": "解毒",
        "rm": "白魔法"
    },
    {
        "src": "バスリプル",
        "dst": "抗睡",
        "rm": "白魔法"
    },
    {
        "src": "プロテス",
        "dst": "护盾",
        "rm": "白魔法"
    },
    {
        "src": "プロテア",
        "dst": "中护盾",
        "rm": "白魔法"
    },
    {
        "src": "バスリプラ",
        "dst": "中抗睡",
        "rm": "白魔法"
    },
    {
        "src": "バウォタ",
        "dst": "抗水",
        "rm": "白魔法"
    },
    {
        "src": "パラナ",
        "dst": "解麻",
        "rm": "白魔法"
    },
    {
        "src": "バウォタラ",
        "dst": "中抗水",
        "rm": "白魔法"
    },
    {
        "src": "バポイズン",
        "dst": "抗毒",
        "rm": "白魔法"
    },
    {
        "src": "アクアベール",
        "dst": "水流幕",
        "rm": "白魔法"
    },
    {
        "src": "バポイゾラ",
        "dst": "中抗毒",
        "rm": "白魔法"
    },
    {
        "src": "シェル",
        "dst": "魔盾",
        "rm": "白魔法"
    },
    {
        "src": "ケアルII",
        "dst": "治疗II",
        "rm": "白魔法"
    },
    {
        "src": "バパライズ",
        "dst": "抗麻",
        "rm": "白魔法"
    },
    {
        "src": "バパライラ",
        "dst": "中抗麻",
        "rm": "白魔法"
    },
    {
        "src": "バエアロ",
        "dst": "抗风",
        "rm": "白魔法"
    },
    {
        "src": "バエアロラ",
        "dst": "中抗风",
        "rm": "白魔法"
    },
    {
        "src": "ブライナ",
        "dst": "复明",
        "rm": "白魔法"
    },
    {
        "src": "バニシュガ",
        "dst": "强放逐",
        "rm": "白魔法"
    },
    {
        "src": "サイレス",
        "dst": "沉默",
        "rm": "白魔法"
    },
    {
        "src": "デオード",
        "dst": "除臭",
        "rm": "白魔法"
    },
    {
        "src": "ディアガ",
        "dst": "天炫",
        "rm": "白魔法"
    },
    {
        "src": "ケアルガ",
        "dst": "愈疗",
        "rm": "白魔法"
    },
    {
        "src": "エンサンダー",
        "dst": "赋雷",
        "rm": "白魔法"
    },
    {
        "src": "バファイ",
        "dst": "抗火",
        "rm": "白魔法"
    },
    {
        "src": "シェルラ",
        "dst": "中魔盾",
        "rm": "白魔法"
    },
    {
        "src": "バファイラ",
        "dst": "中抗火",
        "rm": "白魔法"
    },
    {
        "src": "バブライン",
        "dst": "抗盲",
        "rm": "白魔法"
    },
    {
        "src": "バブライラ",
        "dst": "中抗盲",
        "rm": "白魔法"
    },
    {
        "src": "エンストーン",
        "dst": "赋土",
        "rm": "白魔法"
    },
    {
        "src": "リジェネ",
        "dst": "再生",
        "rm": "白魔法"
    },
    {
        "src": "サイレナ",
        "dst": "解默",
        "rm": "白魔法"
    },
    {
        "src": "ブリンク",
        "dst": "闪躲",
        "rm": "白魔法"
    },
    {
        "src": "スニーク",
        "dst": "消声",
        "rm": "白魔法"
    },
    {
        "src": "エンエアロ",
        "dst": "赋风",
        "rm": "白魔法"
    },
    {
        "src": "バブリザ",
        "dst": "抗冰",
        "rm": "白魔法"
    },
    {
        "src": "バブリザラ",
        "dst": "中抗冰",
        "rm": "白魔法"
    },
    {
        "src": "ケアルIII",
        "dst": "治疗III",
        "rm": "白魔法"
    },
    {
        "src": "エンブリザド",
        "dst": "赋冰",
        "rm": "白魔法"
    },
    {
        "src": "バサイレス",
        "dst": "抗默",
        "rm": "白魔法"
    },
    {
        "src": "バサイレラ",
        "dst": "中抗默",
        "rm": "白魔法"
    },
    {
        "src": "エンファイア",
        "dst": "赋火",
        "rm": "白魔法"
    },
    {
        "src": "バサンダ",
        "dst": "抗雷",
        "rm": "白魔法"
    },
    {
        "src": "レイズ",
        "dst": "复活",
        "rm": "白魔法"
    },
    {
        "src": "リレイズ",
        "dst": "重生",
        "rm": "白魔法"
    },
    {
        "src": "インビジ",
        "dst": "隐身",
        "rm": "白魔法"
    },
    {
        "src": "バサンダラ",
        "dst": "中抗雷",
        "rm": "白魔法"
    },
    {
        "src": "プロテスII",
        "dst": "护盾II",
        "rm": "白魔法"
    },
    {
        "src": "プロテアII",
        "dst": "中护盾II",
        "rm": "白魔法"
    },
    {
        "src": "エンウォータ",
        "dst": "赋水",
        "rm": "白魔法"
    },
    {
        "src": "ストンスキン",
        "dst": "石肤",
        "rm": "白魔法"
    },
    {
        "src": "カーズナ",
        "dst": "解诅",
        "rm": "白魔法"
    },
    {
        "src": "バニシュII",
        "dst": "放逐II",
        "rm": "白魔法"
    },
    {
        "src": "シェルII",
        "dst": "魔盾II",
        "rm": "白魔法"
    },
    {
        "src": "ケアルガII",
        "dst": "愈疗II",
        "rm": "白魔法"
    },
    {
        "src": "ディアII",
        "dst": "天辉II",
        "rm": "白魔法"
    },
    {
        "src": "イレース",
        "dst": "抹除",
        "rm": "白魔法"
    },
    {
        "src": "ファランクス",
        "dst": "方阵",
        "rm": "白魔法"
    },
    {
        "src": "ウィルナ",
        "dst": "解病",
        "rm": "白魔法"
    },
    {
        "src": "テレポデム",
        "dst": "传送迪姆",
        "rm": "白魔法"
    },
    {
        "src": "テレポホラ",
        "dst": "传送霍拉",
        "rm": "白魔法"
    },
    {
        "src": "テレポメア",
        "dst": "传送美亚",
        "rm": "白魔法"
    },
    {
        "src": "シェルラII",
        "dst": "中魔盾II",
        "rm": "白魔法"
    },
    {
        "src": "フラッシュ",
        "dst": "闪光",
        "rm": "白魔法"
    },
    {
        "src": "リジェネII",
        "dst": "再生II",
        "rm": "白魔法"
    },
    {
        "src": "テレポヨト",
        "dst": "传送约特",
        "rm": "白魔法"
    },
    {
        "src": "テレポルテ",
        "dst": "传送露提",
        "rm": "白魔法"
    },
    {
        "src": "バウィルス",
        "dst": "抗病毒",
        "rm": "白魔法"
    },
    {
        "src": "ストナ",
        "dst": "解石",
        "rm": "白魔法"
    },
    {
        "src": "バウィルラ",
        "dst": "中抗病毒",
        "rm": "白魔法"
    },
    {
        "src": "ケアルラ",
        "dst": "救疗",
        "rm": "白魔法"
    },
    {
        "src": "バニシュガII",
        "dst": "强放逐II",
        "rm": "白魔法"
    },
    {
        "src": "ヘイスト",
        "dst": "加速",
        "rm": "白魔法"
    },
    {
        "src": "ケアルIV",
        "dst": "治疗IV",
        "rm": "白魔法"
    },
    {
        "src": "リフレシュ",
        "dst": "醒神",
        "rm": "白魔法"
    },
    {
        "src": "砂尘の阵",
        "dst": "扬沙之阵",
        "rm": "白魔法"
    },
    {
        "src": "テレポヴァズ",
        "dst": "传送瓦兹",
        "rm": "白魔法"
    },
    {
        "src": "バブレイク",
        "dst": "抗石",
        "rm": "白魔法"
    },
    {
        "src": "バブレクラ",
        "dst": "中抗石",
        "rm": "白魔法"
    },
    {
        "src": "豪雨の阵",
        "dst": "豪雨之阵",
        "rm": "白魔法"
    },
    {
        "src": "烈风の阵",
        "dst": "烈风之阵",
        "rm": "白魔法"
    },
    {
        "src": "プロテスIII",
        "dst": "护盾III",
        "rm": "白魔法"
    },
    {
        "src": "プロテアIII",
        "dst": "中护盾III",
        "rm": "白魔法"
    },
    {
        "src": "热波の阵",
        "dst": "高温之阵",
        "rm": "白魔法"
    },
    {
        "src": "リポーズ",
        "dst": "沉静",
        "rm": "白魔法"
    },
    {
        "src": "スナップ",
        "dst": "急速",
        "rm": "白魔法"
    },
    {
        "src": "吹雪の阵",
        "dst": "暴雪之阵",
        "rm": "白魔法"
    },
    {
        "src": "ホーリー",
        "dst": "神圣",
        "rm": "白魔法"
    },
    {
        "src": "エンサンダーII",
        "dst": "赋雷II",
        "rm": "魔法"
    },
    {
        "src": "シェルIII",
        "dst": "魔盾III",
        "rm": "白魔法"
    },
    {
        "src": "ケアルガIII",
        "dst": "救疗III",
        "rm": "白魔法"
    },
    {
        "src": "疾雷の阵",
        "dst": "疾雷之阵",
        "rm": "白魔法"
    },
    {
        "src": "エンストーンII",
        "dst": "赋土II",
        "rm": "魔法"
    },
    {
        "src": "妖雾の阵",
        "dst": "妖雾之阵",
        "rm": "白魔法"
    },
    {
        "src": "リコールジャグ",
        "dst": "回忆嘉格纳",
        "rm": "白魔法"
    },
    {
        "src": "リコールパシュ",
        "dst": "回忆帕什豪",
        "rm": "白魔法"
    },
    {
        "src": "リコールメリファ",
        "dst": "回忆梅里法特",
        "rm": "白魔法"
    },
    {
        "src": "エンエアロII",
        "dst": "赋风II",
        "rm": "魔法"
    },
    {
        "src": "オースピス",
        "dst": "援护",
        "rm": "白魔法"
    },
    {
        "src": "极光の阵",
        "dst": "极光之阵",
        "rm": "白魔法"
    },
    {
        "src": "レイズII",
        "dst": "复活II",
        "rm": "白魔法"
    },
    {
        "src": "リレイズII",
        "dst": "重生II",
        "rm": "白魔法"
    },
    {
        "src": "エンブリザドII",
        "dst": "赋冰II",
        "rm": "魔法"
    },
    {
        "src": "シェルラIII",
        "dst": "魔盾III",
        "rm": "白魔法"
    },
    {
        "src": "エンファイアII",
        "dst": "赋火II",
        "rm": "魔法"
    },
    {
        "src": "フォイル",
        "dst": "妨害",
        "rm": "白魔法"
    },
    {
        "src": "リジェネIII",
        "dst": "再生III",
        "rm": "白魔法"
    },
    {
        "src": "エンウォータII",
        "dst": "赋水II",
        "rm": "魔法"
    },
    {
        "src": "ケアルV",
        "dst": "治疗V",
        "rm": "白魔法"
    },
    {
        "src": "エスナ",
        "dst": "康复",
        "rm": "白魔法"
    },
    {
        "src": "リアクト",
        "dst": "反应",
        "rm": "白魔法"
    },
    {
        "src": "プロテスIV",
        "dst": "护盾IV",
        "rm": "白魔法"
    },
    {
        "src": "プロテアIV",
        "dst": "中护盾IV",
        "rm": "白魔法"
    },
    {
        "src": "イナンデーション",
        "dst": "泛洪",
        "rm": "白魔法"
    },
    {
        "src": "サクリファイス",
        "dst": "献祭",
        "rm": "白魔法"
    },
    {
        "src": "バニシュIII",
        "dst": "放逐III",
        "rm": "白魔法"
    },
    {
        "src": "シェルIV",
        "dst": "魔盾IV",
        "rm": "白魔法"
    },
    {
        "src": "シェルラIV",
        "dst": "中魔盾IV",
        "rm": "白魔法"
    },
    {
        "src": "レイズIII",
        "dst": "复活III",
        "rm": "白魔法"
    },
    {
        "src": "リレイズIII",
        "dst": "重生III",
        "rm": "白魔法"
    },
    {
        "src": "ケアルガIV",
        "dst": "愈疗IV",
        "rm": "白魔法"
    },
    {
        "src": "プロテアV",
        "dst": "护盾V",
        "rm": "白魔法"
    },
    {
        "src": "シェルラV",
        "dst": "魔盾V",
        "rm": "白魔法"
    },
    {
        "src": "ディアIII",
        "dst": "天辉III",
        "rm": "白魔法"
    },
    {
        "src": "パライズII",
        "dst": "麻痹II",
        "rm": "白魔法"
    },
    {
        "src": "スロウII",
        "dst": "减速II",
        "rm": "白魔法"
    },
    {
        "src": "ファランクスII",
        "dst": "方阵II",
        "rm": "白魔法"
    },
    {
        "src": "プロテスV",
        "dst": "护盾V",
        "rm": "白魔法"
    },
    {
        "src": "シェルV",
        "dst": "魔盾V",
        "rm": "白魔法"
    },
    {
        "src": "バアムネジア",
        "dst": "抗失忆",
        "rm": "白魔法"
    },
    {
        "src": "バアムネジラ",
        "dst": "中抗失忆",
        "rm": "白魔法"
    },
    {
        "src": "リジェネIV",
        "dst": "再生IV",
        "rm": "白魔法"
    },
    {
        "src": "ケアルVI",
        "dst": "治疗VI",
        "rm": "白魔法"
    },
    {
        "src": "アディバイト",
        "dst": "增耐力",
        "rm": "白魔法"
    },
    {
        "src": "ゲインバイト",
        "dst": "益耐力",
        "rm": "白魔法"
    },
    {
        "src": "リフレシュII",
        "dst": "醒神II",
        "rm": "白魔法"
    },
    {
        "src": "ケアルラII",
        "dst": "救疗III",
        "rm": "白魔法"
    },
    {
        "src": "アドル",
        "dst": "昏乱",
        "rm": "魔法"
    },
    {
        "src": "アディマイン",
        "dst": "增精神",
        "rm": "白魔法"
    },
    {
        "src": "ゲインマイン",
        "dst": "益精神",
        "rm": "白魔法"
    },
    {
        "src": "エンライト",
        "dst": "赋光",
        "rm": "魔法"
    },
    {
        "src": "悪事千里の策",
        "dst": "恶事千里之策",
        "rm": "魔法"
    },
    {
        "src": "暗中飞跃の策",
        "dst": "暗中行动之策",
        "rm": "白魔法"
    },
    {
        "src": "アディカリス",
        "dst": "增魅力",
        "rm": "白魔法"
    },
    {
        "src": "ゲインカリス",
        "dst": "益魅力",
        "rm": "白魔法"
    },
    {
        "src": "鼓舞激励の策",
        "dst": "鼓舞激励之策",
        "rm": "魔法"
    },
    {
        "src": "クルセード",
        "dst": "战意",
        "rm": "白魔法"
    },
    {
        "src": "アディアジル",
        "dst": "增敏捷",
        "rm": "白魔法"
    },
    {
        "src": "ゲインアジル",
        "dst": "益敏捷",
        "rm": "白魔法"
    },
    {
        "src": "ケアルガV",
        "dst": "愈疗V",
        "rm": "白魔法"
    },
    {
        "src": "アディスト",
        "dst": "增力量",
        "rm": "白魔法"
    },
    {
        "src": "ゲインスト",
        "dst": "益力量",
        "rm": "白魔法"
    },
    {
        "src": "ホーリーII",
        "dst": "神圣II",
        "rm": "白魔法"
    },
    {
        "src": "ストライ",
        "dst": "强打",
        "rm": "白魔法"
    },
    {
        "src": "ケアルラIII",
        "dst": "救疗III",
        "rm": "白魔法"
    },
    {
        "src": "アディイン",
        "dst": "增智力",
        "rm": "白魔法"
    },
    {
        "src": "ゲインイン",
        "dst": "益智力",
        "rm": "白魔法"
    },
    {
        "src": "ヘイストII",
        "dst": "加速II",
        "rm": "白魔法"
    },
    {
        "src": "スナップII",
        "dst": "急速II",
        "rm": "白魔法"
    },
    {
        "src": "アディデック",
        "dst": "增灵巧",
        "rm": "白魔法"
    },
    {
        "src": "ゲインデック",
        "dst": "益灵巧",
        "rm": "白魔法"
    },
    {
        "src": "リジェネV",
        "dst": "再生V",
        "rm": "白魔法"
    },
    {
        "src": "アレイズ",
        "dst": "完全复活",
        "rm": "白魔法"
    },
    {
        "src": "リレイズIV",
        "dst": "重生IV",
        "rm": "白魔法"
    },
    {
        "src": "フルケア",
        "dst": "痊愈",
        "rm": "白魔法"
    },
    {
        "src": "エンライトII",
        "dst": "赋光II",
        "rm": "白魔法"
    },
    {
        "src": "砂尘の阵II",
        "dst": "扬沙之阵II",
        "rm": "白魔法"
    },
    {
        "src": "豪雨の阵II",
        "dst": "豪雨之阵II",
        "rm": "白魔法"
    },
    {
        "src": "烈风の阵II",
        "dst": "烈风之阵II",
        "rm": "白魔法"
    },
    {
        "src": "热波の阵II",
        "dst": "高温之阵II",
        "rm": "白魔法"
    },
    {
        "src": "吹雪の阵II",
        "dst": "暴雪之阵II",
        "rm": "白魔法"
    },
    {
        "src": "疾雷の阵II",
        "dst": "疾雷之阵II",
        "rm": "白魔法"
    },
    {
        "src": "妖雾の阵II",
        "dst": "妖雾之阵II",
        "rm": "白魔法"
    },
    {
        "src": "极光の阵II",
        "dst": "极光之阵II",
        "rm": "白魔法"
    },
    {
        "src": "アドルII",
        "dst": "昏乱II",
        "rm": "白魔法"
    },
    {
        "src": "リフレシュIII",
        "dst": "醒神III",
        "rm": "白魔法"
    },
    {
        "src": "ストライII",
        "dst": "强打II",
        "rm": "白魔法"
    },
    {
        "src": "ストーン",
        "dst": "飞石",
        "rm": "黑魔法"
    },
    {
        "src": "ポイズン",
        "dst": "施毒",
        "rm": "黑魔法"
    },
    {
        "src": "ブライン",
        "dst": "失明",
        "rm": "黑魔法"
    },
    {
        "src": "ウォータ",
        "dst": "流水",
        "rm": "黑魔法"
    },
    {
        "src": "メルトン",
        "dst": "熔毁",
        "rm": "黑魔法"
    },
    {
        "src": "エアロ",
        "dst": "疾风",
        "rm": "黑魔法"
    },
    {
        "src": "バイオ",
        "dst": "毒菌",
        "rm": "黑魔法"
    },
    {
        "src": "ブレイズスパイク",
        "dst": "火棘屏障",
        "rm": "黑魔法"
    },
    {
        "src": "ドレイン",
        "dst": "吸收",
        "rm": "黑魔法"
    },
    {
        "src": "ファイア",
        "dst": "火炎",
        "rm": "黑魔法"
    },
    {
        "src": "ストンガ",
        "dst": "垒石",
        "rm": "黑魔法"
    },
    {
        "src": "ショック",
        "dst": "激震",
        "rm": "黑魔法"
    },
    {
        "src": "ブリザド",
        "dst": "冰结",
        "rm": "黑魔法"
    },
    {
        "src": "デジョン",
        "dst": "返回",
        "rm": "黑魔法"
    },
    {
        "src": "ラスプ",
        "dst": "锉伤",
        "rm": "黑魔法"
    },
    {
        "src": "土门の计",
        "dst": "土门之计",
        "rm": "黑魔法"
    },
    {
        "src": "ウォタガ",
        "dst": "狂水",
        "rm": "黑魔法"
    },
    {
        "src": "スリプル",
        "dst": "催眠",
        "rm": "黑魔法"
    },
    {
        "src": "アイススパイク",
        "dst": "冰棘屏障",
        "rm": "黑魔法"
    },
    {
        "src": "チョーク",
        "dst": "风压",
        "rm": "黑魔法"
    },
    {
        "src": "アスピル",
        "dst": "摄魔",
        "rm": "黑魔法"
    },
    {
        "src": "水门の计",
        "dst": "水门之计",
        "rm": "黑魔法"
    },
    {
        "src": "サンダー",
        "dst": "闪雷",
        "rm": "黑魔法"
    },
    {
        "src": "グラビデ",
        "dst": "重力",
        "rm": "黑魔法"
    },
    {
        "src": "フロスト",
        "dst": "寒冰",
        "rm": "黑魔法"
    },
    {
        "src": "风门の计",
        "dst": "风门之计",
        "rm": "黑魔法"
    },
    {
        "src": "エアロガ",
        "dst": "暴风",
        "rm": "黑魔法"
    },
    {
        "src": "ポイゾガ",
        "dst": "强施毒",
        "rm": "黑魔法"
    },
    {
        "src": "バーン",
        "dst": "焦灼",
        "rm": "黑魔法"
    },
    {
        "src": "火门の计",
        "dst": "火门之计",
        "rm": "黑魔法"
    },
    {
        "src": "トラクタ",
        "dst": "牵引",
        "rm": "黑魔法"
    },
    {
        "src": "ストンラ",
        "dst": "坚石",
        "rm": "黑魔法"
    },
    {
        "src": "ストーンII",
        "dst": "飞石II",
        "rm": "黑魔法"
    },
    {
        "src": "氷门の计",
        "dst": "冰门之计",
        "rm": "黑魔法"
    },
    {
        "src": "ドラウン",
        "dst": "沉溺",
        "rm": "黑魔法"
    },
    {
        "src": "ファイガ",
        "dst": "爆炎",
        "rm": "黑魔法"
    },
    {
        "src": "雷门の计",
        "dst": "雷门之计",
        "rm": "黑魔法"
    },
    {
        "src": "エスケプ",
        "dst": "逃脱",
        "rm": "黑魔法"
    },
    {
        "src": "ウォータII",
        "dst": "流水II",
        "rm": "黑魔法"
    },
    {
        "src": "ショックスパイク",
        "dst": "电棘屏障",
        "rm": "黑魔法"
    },
    {
        "src": "暗门の计",
        "dst": "暗门之计",
        "rm": "黑魔法"
    },
    {
        "src": "ウォタラ",
        "dst": "激水",
        "rm": "黑魔法"
    },
    {
        "src": "スリプガ",
        "dst": "强催眠",
        "rm": "黑魔法"
    },
    {
        "src": "アブゾマイン",
        "dst": "吸精神",
        "rm": "黑魔法"
    },
    {
        "src": "ブリザガ",
        "dst": "冰封",
        "rm": "黑魔法"
    },
    {
        "src": "ディスペル",
        "dst": "驱魔",
        "rm": "黑魔法"
    },
    {
        "src": "光门の计",
        "dst": "光门之计",
        "rm": "黑魔法"
    },
    {
        "src": "アブゾカリス",
        "dst": "吸魅力",
        "rm": "黑魔法"
    },
    {
        "src": "エアロII",
        "dst": "疾风II",
        "rm": "黑魔法"
    },
    {
        "src": "バイオII",
        "dst": "毒菌II",
        "rm": "黑魔法"
    },
    {
        "src": "ディストラ",
        "dst": "分心",
        "rm": "黑魔法"
    },
    {
        "src": "アブゾバイト",
        "dst": "吸耐力",
        "rm": "黑魔法"
    },
    {
        "src": "エアロラ",
        "dst": "烈风",
        "rm": "黑魔法"
    },
    {
        "src": "サンダガ",
        "dst": "暴雷",
        "rm": "黑魔法"
    },
    {
        "src": "アブゾアジル",
        "dst": "吸敏捷",
        "rm": "黑魔法"
    },
    {
        "src": "ファイアII",
        "dst": "火炎II",
        "rm": "黑魔法"
    },
    {
        "src": "アブゾイン",
        "dst": "吸智力",
        "rm": "黑魔法"
    },
    {
        "src": "ストンガII",
        "dst": "垒石II",
        "rm": "黑魔法"
    },
    {
        "src": "デジョンII",
        "dst": "返回II",
        "rm": "黑魔法"
    },
    {
        "src": "ファイラ",
        "dst": "烈炎",
        "rm": "黑魔法"
    },
    {
        "src": "スリプルII",
        "dst": "催眠II",
        "rm": "黑魔法"
    },
    {
        "src": "アブゾデック",
        "dst": "吸灵巧",
        "rm": "黑魔法"
    },
    {
        "src": "ブリザドII",
        "dst": "冰结II",
        "rm": "黑魔法"
    },
    {
        "src": "フラズル",
        "dst": "疲敝",
        "rm": "黑魔法"
    },
    {
        "src": "ポイズンII",
        "dst": "施毒II",
        "rm": "黑魔法"
    },
    {
        "src": "アブゾースト",
        "dst": "吸力量",
        "rm": "黑魔法"
    },
    {
        "src": "ウォタガII",
        "dst": "狂水II",
        "rm": "黑魔法"
    },
    {
        "src": "アブゾタック",
        "dst": "吸技力",
        "rm": "黑魔法"
    },
    {
        "src": "ブリザラ",
        "dst": "冰冻",
        "rm": "黑魔法"
    },
    {
        "src": "サンダーII",
        "dst": "闪雷II",
        "rm": "黑魔法"
    },
    {
        "src": "虚诱掩杀の策",
        "dst": "虚诱掩杀之策",
        "rm": "黑魔法"
    },
    {
        "src": "エアロガII",
        "dst": "暴风II",
        "rm": "黑魔法"
    },
    {
        "src": "フリーズ",
        "dst": "玄冰",
        "rm": "黑魔法"
    },
    {
        "src": "サンダラ",
        "dst": "震雷",
        "rm": "黑魔法"
    },
    {
        "src": "ストーンIII",
        "dst": "飞石III",
        "rm": "黑魔法"
    },
    {
        "src": "トルネド",
        "dst": "龙卷",
        "rm": "黑魔法"
    },
    {
        "src": "ファイガII",
        "dst": "爆炎II",
        "rm": "黑魔法"
    },
    {
        "src": "クエイク",
        "dst": "地震",
        "rm": "黑魔法"
    },
    {
        "src": "ウォータIII",
        "dst": "流水III",
        "rm": "黑魔法"
    },
    {
        "src": "リトレース",
        "dst": "追溯",
        "rm": "黑魔法"
    },
    {
        "src": "スリプガII",
        "dst": "强催眠II",
        "rm": "黑魔法"
    },
    {
        "src": "バースト",
        "dst": "磁暴",
        "rm": "黑魔法"
    },
    {
        "src": "ブリザガII",
        "dst": "冰封II",
        "rm": "黑魔法"
    },
    {
        "src": "フラッド",
        "dst": "洪水",
        "rm": "黑魔法"
    },
    {
        "src": "エアロIII",
        "dst": "疾风III",
        "rm": "黑魔法"
    },
    {
        "src": "フレア",
        "dst": "核爆",
        "rm": "黑魔法"
    },
    {
        "src": "サンダガII",
        "dst": "暴雷II",
        "rm": "黑魔法"
    },
    {
        "src": "アブゾアキュル",
        "dst": "吸命中",
        "rm": "黑魔法"
    },
    {
        "src": "ファイアIII",
        "dst": "火炎III",
        "rm": "黑魔法"
    },
    {
        "src": "ドレインII",
        "dst": "吸收II",
        "rm": "黑魔法"
    },
    {
        "src": "ストンガIII",
        "dst": "垒石III",
        "rm": "黑魔法"
    },
    {
        "src": "ブリザドIII",
        "dst": "冰结III",
        "rm": "黑魔法"
    },
    {
        "src": "ウォタガIII",
        "dst": "狂水III",
        "rm": "黑魔法"
    },
    {
        "src": "サンダーIII",
        "dst": "闪雷III",
        "rm": "黑魔法"
    },
    {
        "src": "エアロガIII",
        "dst": "暴风III",
        "rm": "黑魔法"
    },
    {
        "src": "ストーンIV",
        "dst": "飞石IV",
        "rm": "黑魔法"
    },
    {
        "src": "ファイガIII",
        "dst": "爆炎III",
        "rm": "黑魔法"
    },
    {
        "src": "ウォータIV",
        "dst": "流水IV",
        "rm": "黑魔法"
    },
    {
        "src": "ストンラII",
        "dst": "坚石II",
        "rm": "黑魔法"
    },
    {
        "src": "ブリザガIII",
        "dst": "冰封III",
        "rm": "黑魔法"
    },
    {
        "src": "ドレッドスパイク",
        "dst": "暗棘屏障",
        "rm": "黑魔法"
    },
    {
        "src": "エアロIV",
        "dst": "疾风IV",
        "rm": "黑魔法"
    },
    {
        "src": "ファイアIV",
        "dst": "火炎IV",
        "rm": "黑魔法"
    },
    {
        "src": "サンダガIII",
        "dst": "暴雷III",
        "rm": "黑魔法"
    },
    {
        "src": "ブリザドIV",
        "dst": "冰结IV",
        "rm": "黑魔法"
    },
    {
        "src": "サンダーIV",
        "dst": "闪雷IV",
        "rm": "黑魔法"
    },
    {
        "src": "ウォタラII",
        "dst": "激水II",
        "rm": "黑魔法"
    },
    {
        "src": "フレアII",
        "dst": "核爆II",
        "rm": "黑魔法"
    },
    {
        "src": "フリーズII",
        "dst": "玄冰II",
        "rm": "黑魔法"
    },
    {
        "src": "トルネドII",
        "dst": "龙卷II",
        "rm": "黑魔法"
    },
    {
        "src": "クエイクII",
        "dst": "地震II",
        "rm": "黑魔法"
    },
    {
        "src": "バーストII",
        "dst": "磁暴II",
        "rm": "黑魔法"
    },
    {
        "src": "フラッドII",
        "dst": "洪水II",
        "rm": "黑魔法"
    },
    {
        "src": "バイオIII",
        "dst": "毒菌III",
        "rm": "黑魔法"
    },
    {
        "src": "ブラインII",
        "dst": "失明II",
        "rm": "黑魔法"
    },
    {
        "src": "ストーンV",
        "dst": "飞石V",
        "rm": "黑魔法"
    },
    {
        "src": "アスピルII",
        "dst": "吸魔II",
        "rm": "黑魔法"
    },
    {
        "src": "ウォータV",
        "dst": "流水V",
        "rm": "黑魔法"
    },
    {
        "src": "エアロラII",
        "dst": "烈风II",
        "rm": "黑魔法"
    },
    {
        "src": "ストンジャ",
        "dst": "崩石",
        "rm": "黑魔法"
    },
    {
        "src": "エアロV",
        "dst": "疾风V",
        "rm": "黑魔法"
    },
    {
        "src": "ウォタジャ",
        "dst": "骇水",
        "rm": "黑魔法"
    },
    {
        "src": "ブレイク",
        "dst": "石化",
        "rm": "黑魔法"
    },
    {
        "src": "ディストラII",
        "dst": "分心II",
        "rm": "黑魔法"
    },
    {
        "src": "エンダーク",
        "dst": "赋暗",
        "rm": "魔法"
    },
    {
        "src": "ファイラII",
        "dst": "烈炎II",
        "rm": "黑魔法"
    },
    {
        "src": "ファイアV",
        "dst": "火炎V",
        "rm": "黑魔法"
    },
    {
        "src": "エアロジャ",
        "dst": "飙风",
        "rm": "黑魔法"
    },
    {
        "src": "ブリザドV",
        "dst": "冰结V",
        "rm": "黑魔法"
    },
    {
        "src": "ファイジャ",
        "dst": "炽炎",
        "rm": "黑魔法"
    },
    {
        "src": "ブリザラII",
        "dst": "冰冻II",
        "rm": "黑魔法"
    },
    {
        "src": "アブゾアトリ",
        "dst": "吸特性",
        "rm": "黑魔法"
    },
    {
        "src": "サンダーV",
        "dst": "闪雷V",
        "rm": "黑魔法"
    },
    {
        "src": "フラズルII",
        "dst": "疲敝II",
        "rm": "黑魔法"
    },
    {
        "src": "ブリザジャ",
        "dst": "冰澈",
        "rm": "黑魔法"
    },
    {
        "src": "コメット",
        "dst": "彗星",
        "rm": "黑魔法"
    },
    {
        "src": "ブレクガ",
        "dst": "强石化",
        "rm": "黑魔法"
    },
    {
        "src": "サンダラII",
        "dst": "震雷II",
        "rm": "黑魔法"
    },
    {
        "src": "サンダジャ",
        "dst": "霹雷",
        "rm": "黑魔法"
    },
    {
        "src": "グラビデII",
        "dst": "重力II",
        "rm": "黑魔法"
    },
    {
        "src": "メテオ",
        "dst": "陨石",
        "rm": "黑魔法"
    },
    {
        "src": "ストーンVI",
        "dst": "飞石VI",
        "rm": "黑魔法"
    },
    {
        "src": "ウォータVI",
        "dst": "流水VI",
        "rm": "黑魔法"
    },
    {
        "src": "エアロVI",
        "dst": "疾风VI",
        "rm": "黑魔法"
    },
    {
        "src": "ファイアVI",
        "dst": "火炎VI",
        "rm": "黑魔法"
    },
    {
        "src": "ブリザドVI",
        "dst": "冰结VI",
        "rm": "黑魔法"
    },
    {
        "src": "サンダーVI",
        "dst": "闪雷VI",
        "rm": "黑魔法"
    },
    {
        "src": "エンダークII",
        "dst": "赋暗II",
        "rm": "黑魔法"
    },
    {
        "src": "ドレインIII",
        "dst": "吸收III",
        "rm": "黑魔法"
    },
    {
        "src": "アスピルIII",
        "dst": "吸魔III",
        "rm": "黑魔法"
    },
    {
        "src": "デス",
        "dst": "即死",
        "rm": "黑魔法"
    },
    {
        "src": "ディストラIII",
        "dst": "分心III",
        "rm": "黑魔法"
    },
    {
        "src": "フラズルIII",
        "dst": "疲敝III",
        "rm": "黑魔法"
    },
    {
        "src": "土门の计II",
        "dst": "土门之计II",
        "rm": "黑魔法"
    },
    {
        "src": "水门の计II",
        "dst": "水门之计II",
        "rm": "黑魔法"
    },
    {
        "src": "风门の计II",
        "dst": "风门之计II",
        "rm": "黑魔法"
    },
    {
        "src": "火门の计II",
        "dst": "火门之计II",
        "rm": "黑魔法"
    },
    {
        "src": "氷门の计II",
        "dst": "冰门之计II",
        "rm": "黑魔法"
    },
    {
        "src": "雷门の计II",
        "dst": "雷门之计II",
        "rm": "黑魔法"
    },
    {
        "src": "暗门の计II",
        "dst": "暗门之计II",
        "rm": "黑魔法"
    },
    {
        "src": "光门の计II",
        "dst": "光门之计II",
        "rm": "黑魔法"
    },
    {
        "src": "ストンラIII",
        "dst": "坚石III",
        "rm": "黑魔法"
    },
    {
        "src": "ウォタラIII",
        "dst": "激水III",
        "rm": "黑魔法"
    },
    {
        "src": "エアロラIII",
        "dst": "烈风III",
        "rm": "黑魔法"
    },
    {
        "src": "ファイラIII",
        "dst": "烈炎III",
        "rm": "黑魔法"
    },
    {
        "src": "ブリザラIII",
        "dst": "冰冻III",
        "rm": "黑魔法"
    },
    {
        "src": "サンダラIII",
        "dst": "震雷III",
        "rm": "黑魔法"
    },
    {
        "src": "カムラナート",
        "dst": "卡姆拉纳特",
        "rm": "朱诺大公国大公"
    },
    {
        "src": "エルドナーシュ",
        "dst": "埃尔德纳修",
        "rm": "大公之弟（实际是兄）"
    },
    {
        "src": "星の神子",
        "dst": "星之神子",
        "rm": "温达斯的领袖，被温达斯人认为是现人神"
    },
    {
        "src": "シャントット",
        "dst": "香托托",
        "rm": "温达斯三博士之一"
    },
    {
        "src": "ナジ",
        "dst": "纳吉",
        "rm": "秘银枪手队的一员"
    },
    {
        "src": "クピピ",
        "dst": "库皮皮",
        "rm": "温达斯天之塔书记官"
    },
    {
        "src": "エグセニミル",
        "dst": "埃格塞尼米尔",
        "rm": "人物"
    },
    {
        "src": "アヤメ",
        "dst": "阿雅梅",
        "rm": "人物"
    },
    {
        "src": "ナナー・ミーゴ",
        "dst": "娜娜·米果",
        "rm": "人物"
    },
    {
        "src": "クリルラ",
        "dst": "克莉尔拉",
        "rm": "人物"
    },
    {
        "src": "フォルカー",
        "dst": "福尔卡",
        "rm": "人物"
    },
    {
        "src": "アジドマルジド",
        "dst": "阿吉多玛鲁吉多",
        "rm": "人物"
    },
    {
        "src": "トリオン",
        "dst": "特里昂",
        "rm": "人物"
    },
    {
        "src": "ザイド",
        "dst": "扎伊德",
        "rm": "人物"
    },
    {
        "src": "ライオン",
        "dst": "莱昂",
        "rm": "人物"
    },
    {
        "src": "テンゼン",
        "dst": "典膳",
        "rm": "人物"
    },
    {
        "src": "ミリ・アリアポー",
        "dst": "米莉·阿里亚珀",
        "rm": "人物"
    },
    {
        "src": "ヴァレンラール",
        "dst": "瓦伦拉尔",
        "rm": "人物"
    },
    {
        "src": "ヨアヒム",
        "dst": "约阿希姆",
        "rm": "人物"
    },
    {
        "src": "ナジャ・サラヒム",
        "dst": "纳贾·萨拉希姆",
        "rm": "人物"
    },
    {
        "src": "プリッシュ",
        "dst": "普莉修",
        "rm": "人物"
    },
    {
        "src": "ウルミア",
        "dst": "乌尔米亚",
        "rm": "人物"
    },
    {
        "src": "スカリーZ",
        "dst": "斯卡利Z",
        "rm": "人物"
    },
    {
        "src": "チェルキキ",
        "dst": "切露奇奇",
        "rm": "人物"
    },
    {
        "src": "アイアンイーター",
        "dst": "铁食者",
        "rm": "人物"
    },
    {
        "src": "ゲッショー",
        "dst": "戈修",
        "rm": "人物"
    },
    {
        "src": "ガダラル",
        "dst": "加达拉尔",
        "rm": "人物"
    },
    {
        "src": "ライニマード",
        "dst": "莱尼玛德",
        "rm": "人物"
    },
    {
        "src": "イングリッド",
        "dst": "英格丽德",
        "rm": "人物"
    },
    {
        "src": "レコ・ハボッカ",
        "dst": "雷科·哈博卡",
        "rm": "人物"
    },
    {
        "src": "ナシュメラ",
        "dst": "娜修梅拉",
        "rm": "人物"
    },
    {
        "src": "ザザーグ",
        "dst": "扎扎格",
        "rm": "人物"
    },
    {
        "src": "アヴゼン",
        "dst": "阿维森",
        "rm": "人物"
    },
    {
        "src": "メネジン",
        "dst": "梅内金",
        "rm": "人物"
    },
    {
        "src": "サクラ",
        "dst": "樱",
        "rm": "人物"
    },
    {
        "src": "ルザフ",
        "dst": "鲁扎夫",
        "rm": "人物"
    },
    {
        "src": "ナジュリス",
        "dst": "纳朱里斯",
        "rm": "人物"
    },
    {
        "src": "アルド",
        "dst": "阿尔多",
        "rm": "人物"
    },
    {
        "src": "モーグリ",
        "dst": "莫古力",
        "rm": "人物"
    },
    {
        "src": "ファブリニクス",
        "dst": "法布里尼克斯",
        "rm": "人物"
    },
    {
        "src": "マート",
        "dst": "马特",
        "rm": "人物"
    },
    {
        "src": "カラハバルハ",
        "dst": "卡拉哈巴鲁哈",
        "rm": "人物"
    },
    {
        "src": "シド",
        "dst": "西德",
        "rm": "人物"
    },
    {
        "src": "ギルガメッシュ",
        "dst": "吉尔伽美什",
        "rm": "人物"
    },
    {
        "src": "アレヴァト",
        "dst": "阿雷瓦特",
        "rm": "人物"
    },
    {
        "src": "セミ・ラフィーナ",
        "dst": "塞米·拉菲娜",
        "rm": "人物"
    },
    {
        "src": "エリヴィラ",
        "dst": "艾莉维拉",
        "rm": "人物"
    },
    {
        "src": "ノユリ",
        "dst": "诺尤里",
        "rm": "人物"
    },
    {
        "src": "ルー・マカラッカ",
        "dst": "卢·马卡拉卡",
        "rm": "人物"
    },
    {
        "src": "フェリアスコフィン",
        "dst": "费里亚斯科芬",
        "rm": "人物"
    },
    {
        "src": "リリゼット",
        "dst": "莉莉泽特",
        "rm": "人物"
    },
    {
        "src": "ミュモル",
        "dst": "缪莫尔",
        "rm": "人物"
    },
    {
        "src": "ウカ・トトゥリン",
        "dst": "乌卡·托图林",
        "rm": "人物"
    },
    {
        "src": "クララ",
        "dst": "克拉拉",
        "rm": "人物"
    },
    {
        "src": "ロマー・ミーゴ",
        "dst": "洛玛·米果",
        "rm": "人物"
    },
    {
        "src": "クイン・ハスデンナ",
        "dst": "库茵·哈丝登娜",
        "rm": "人物"
    },
    {
        "src": "ラーアル",
        "dst": "拉阿尔",
        "rm": "人物"
    },
    {
        "src": "コルモル",
        "dst": "科尔莫尔",
        "rm": "人物"
    },
    {
        "src": "ピエージェ",
        "dst": "皮耶杰",
        "rm": "人物"
    },
    {
        "src": "アプルル",
        "dst": "阿普露露",
        "rm": "人物"
    },
    {
        "src": "ジャコ",
        "dst": "贾科",
        "rm": "人物"
    },
    {
        "src": "フラヴィリア",
        "dst": "弗拉维利亚",
        "rm": "人物"
    },
    {
        "src": "ウェイレア",
        "dst": "韦亚雷亚",
        "rm": "人物"
    },
    {
        "src": "アベンツィオ",
        "dst": "阿本齐奥",
        "rm": "人物"
    },
    {
        "src": "ルガジーン",
        "dst": "卢加津",
        "rm": "人物"
    },
    {
        "src": "クッキーチェブキー",
        "dst": "库奇切布奇",
        "rm": "人物"
    },
    {
        "src": "マルグレート",
        "dst": "玛格丽特",
        "rm": "人物"
    },
    {
        "src": "チャチャルン",
        "dst": "查查伦",
        "rm": "人物"
    },
    {
        "src": "レイ・ランガヴォ",
        "dst": "雷·兰加沃",
        "rm": "人物"
    },
    {
        "src": "アシェラ",
        "dst": "阿谢拉",
        "rm": "人物"
    },
    {
        "src": "マヤコフ",
        "dst": "马雅科夫",
        "rm": "人物"
    },
    {
        "src": "クルタダ",
        "dst": "库尔塔达",
        "rm": "人物"
    },
    {
        "src": "アーデルハイト",
        "dst": "阿德尔海特",
        "rm": "人物"
    },
    {
        "src": "アムチュチュ",
        "dst": "阿姆楚楚",
        "rm": "人物"
    },
    {
        "src": "ブリジッド",
        "dst": "布里吉德",
        "rm": "人物"
    },
    {
        "src": "ミルドリオン",
        "dst": "米尔德里昂",
        "rm": "人物"
    },
    {
        "src": "ハルヴァー",
        "dst": "哈尔瓦尔",
        "rm": "人物"
    },
    {
        "src": "ロンジェルツ",
        "dst": "隆杰尔茨",
        "rm": "人物"
    },
    {
        "src": "レオノアーヌ",
        "dst": "莱昂诺阿努",
        "rm": "人物"
    },
    {
        "src": "マクシミリアン",
        "dst": "马克西米利安",
        "rm": "人物"
    },
    {
        "src": "カイルパイル",
        "dst": "凯尔派尔",
        "rm": "人物"
    },
    {
        "src": "ロベルアクベル",
        "dst": "罗贝拉克贝尔",
        "rm": "人物"
    },
    {
        "src": "クポフリート",
        "dst": "库波弗里特",
        "rm": "人物"
    },
    {
        "src": "セルテウス",
        "dst": "塞尔特乌斯",
        "rm": "人物"
    },
    {
        "src": "ヨランオラン",
        "dst": "约兰奥兰",
        "rm": "人物"
    },
    {
        "src": "シルヴィ",
        "dst": "西尔维",
        "rm": "人物"
    },
    {
        "src": "アブクーバ",
        "dst": "阿布库巴",
        "rm": "人物"
    },
    {
        "src": "バラモア",
        "dst": "巴拉莫尔",
        "rm": "人物"
    },
    {
        "src": "オーグスト",
        "dst": "奥古斯特",
        "rm": "人物"
    },
    {
        "src": "ロスレーシャ",
        "dst": "罗斯莱莎",
        "rm": "人物"
    },
    {
        "src": "テオドール",
        "dst": "特奥多尔",
        "rm": "人物"
    },
    {
        "src": "ウルゴア",
        "dst": "乌尔戈阿",
        "rm": "人物"
    },
    {
        "src": "マッキーチェブキー",
        "dst": "马奇切布奇",
        "rm": "人物"
    },
    {
        "src": "キング・オブ・ハーツ",
        "dst": "红心之王",
        "rm": "人物"
    },
    {
        "src": "モリマー",
        "dst": "莫里默",
        "rm": "人物"
    },
    {
        "src": "ダラクァルン",
        "dst": "达拉夸卢恩",
        "rm": "人物"
    },
    {
        "src": "イロハ",
        "dst": "五郎八",
        "rm": "人物"
    },
    {
        "src": "ユグナス",
        "dst": "尤格纳斯",
        "rm": "人物"
    },
    {
        "src": "モンブロー",
        "dst": "蒙布罗",
        "rm": "人物"
    },
    {
        "src": "コーネリア",
        "dst": "科妮莉亚",
        "rm": "人物"
    },
    {
        "src": "ナジャ",
        "dst": "纳贾",
        "rm": "人物"
    },
    {
        "src": "土門の計",
        "dst": "土门之计",
        "rm": "魔法"
    },
    {
        "src": "水門の計",
        "dst": "水门之计",
        "rm": "魔法"
    },
    {
        "src": "風門の計",
        "dst": "风门之计",
        "rm": "魔法"
    },
    {
        "src": "火門の計",
        "dst": "火门之计",
        "rm": "魔法"
    },
    {
        "src": "氷門の計",
        "dst": "冰门之计",
        "rm": "魔法"
    },
    {
        "src": "雷門の計",
        "dst": "雷门之计",
        "rm": "魔法"
    },
    {
        "src": "闇門の計",
        "dst": "暗门之计",
        "rm": "魔法"
    },
    {
        "src": "光門の計",
        "dst": "光门之计",
        "rm": "魔法"
    },
    {
        "src": "虚誘掩殺の策",
        "dst": "虚诱掩杀之策",
        "rm": "魔法"
    },
    {
        "src": "火精霊召喚",
        "dst": "火精灵召唤",
        "rm": "魔法"
    },
    {
        "src": "氷精霊召喚",
        "dst": "冰精灵召唤",
        "rm": "魔法"
    },
    {
        "src": "風精霊召喚",
        "dst": "风精灵召唤",
        "rm": "魔法"
    },
    {
        "src": "土精霊召喚",
        "dst": "土精灵召唤",
        "rm": "魔法"
    },
    {
        "src": "雷精霊召喚",
        "dst": "雷精灵召唤",
        "rm": "魔法"
    },
    {
        "src": "水精霊召喚",
        "dst": "水精灵召唤",
        "rm": "魔法"
    },
    {
        "src": "光精霊召喚",
        "dst": "光精灵召唤",
        "rm": "魔法"
    },
    {
        "src": "闇精霊召喚",
        "dst": "暗精灵召唤",
        "rm": "魔法"
    },
    {
        "src": "カーバンクル召喚",
        "dst": "宝石兽召唤",
        "rm": "魔法"
    },
    {
        "src": "フェンリル召喚",
        "dst": "芬里尔召唤",
        "rm": "魔法"
    },
    {
        "src": "イフリート召喚",
        "dst": "伊弗利特召唤",
        "rm": "魔法"
    },
    {
        "src": "タイタン召喚",
        "dst": "泰坦召唤",
        "rm": "魔法"
    },
    {
        "src": "リヴァイアサン召喚",
        "dst": "利维亚桑召唤",
        "rm": "魔法"
    },
    {
        "src": "ガルーダ召喚",
        "dst": "迦楼罗召唤",
        "rm": "魔法"
    },
    {
        "src": "シヴァ召喚",
        "dst": "希瓦召唤",
        "rm": "魔法"
    },
    {
        "src": "ラムウ召喚",
        "dst": "拉姆召唤",
        "rm": "魔法"
    },
    {
        "src": "ディアボロス召喚",
        "dst": "迪亚波罗斯召唤",
        "rm": "魔法"
    },
    {
        "src": "オーディン召喚",
        "dst": "奥丁召唤",
        "rm": "魔法"
    },
    {
        "src": "アレキサンダー召喚",
        "dst": "亚历山大召唤",
        "rm": "魔法"
    },
    {
        "src": "ケット・シー召喚",
        "dst": "凯特西召唤",
        "rm": "魔法"
    },
    {
        "src": "暗中飛躍の策",
        "dst": "暗中飞跃之策",
        "rm": "魔法"
    },
    {
        "src": "物見の術:壱",
        "dst": "侦察之术:壹",
        "rm": "魔法"
    },
    {
        "src": "哀車の術:壱",
        "dst": "哀车之术:壹",
        "rm": "魔法"
    },
    {
        "src": "火遁の術:壱",
        "dst": "火遁之术:壹",
        "rm": "魔法"
    },
    {
        "src": "火遁の術:弐",
        "dst": "火遁之术:贰",
        "rm": "魔法"
    },
    {
        "src": "火遁の術:参",
        "dst": "火遁之术:叁",
        "rm": "魔法"
    },
    {
        "src": "氷遁の術:壱",
        "dst": "冰遁之术:壹",
        "rm": "魔法"
    },
    {
        "src": "氷遁の術:弐",
        "dst": "冰遁之术:贰",
        "rm": "魔法"
    },
    {
        "src": "氷遁の術:参",
        "dst": "冰遁之术:叁",
        "rm": "魔法"
    },
    {
        "src": "風遁の術:壱",
        "dst": "风遁之术:壹",
        "rm": "魔法"
    },
    {
        "src": "風遁の術:弐",
        "dst": "风遁之术:贰",
        "rm": "魔法"
    },
    {
        "src": "風遁の術:参",
        "dst": "风遁之术:叁",
        "rm": "魔法"
    },
    {
        "src": "土遁の術:壱",
        "dst": "土遁之术:壹",
        "rm": "魔法"
    },
    {
        "src": "土遁の術:弐",
        "dst": "土遁之术:贰",
        "rm": "魔法"
    },
    {
        "src": "土遁の術:参",
        "dst": "土遁之术:叁",
        "rm": "魔法"
    },
    {
        "src": "雷遁の術:壱",
        "dst": "雷遁之术:壹",
        "rm": "魔法"
    },
    {
        "src": "雷遁の術:弐",
        "dst": "雷遁之术:贰",
        "rm": "魔法"
    },
    {
        "src": "雷遁の術:参",
        "dst": "雷遁之术:叁",
        "rm": "魔法"
    },
    {
        "src": "水遁の術:壱",
        "dst": "水遁之术:壹",
        "rm": "魔法"
    },
    {
        "src": "水遁の術:弐",
        "dst": "水遁之术:贰",
        "rm": "魔法"
    },
    {
        "src": "水遁の術:参",
        "dst": "水遁之术:叁",
        "rm": "魔法"
    },
    {
        "src": "空蝉の術:壱",
        "dst": "空蝉之术:壹",
        "rm": "魔法"
    },
    {
        "src": "空蝉の術:弐",
        "dst": "空蝉之术:贰",
        "rm": "魔法"
    },
    {
        "src": "空蝉の術:参",
        "dst": "空蝉之术:叁",
        "rm": "魔法"
    },
    {
        "src": "呪縛の術:壱",
        "dst": "咒缚之术:壹",
        "rm": "魔法"
    },
    {
        "src": "呪縛の術:弐",
        "dst": "咒缚之术:贰",
        "rm": "魔法"
    },
    {
        "src": "呪縛の術:参",
        "dst": "咒缚之术:叁",
        "rm": "魔法"
    },
    {
        "src": "捕縄の術:壱",
        "dst": "捕绳之术:壹",
        "rm": "魔法"
    },
    {
        "src": "捕縄の術:弐",
        "dst": "捕绳之术:贰",
        "rm": "魔法"
    },
    {
        "src": "捕縄の術:参",
        "dst": "捕绳之术:叁",
        "rm": "魔法"
    },
    {
        "src": "暗闇の術:壱",
        "dst": "暗黑之术:壹",
        "rm": "魔法"
    },
    {
        "src": "暗闇の術:弐",
        "dst": "暗黑之术:贰",
        "rm": "魔法"
    },
    {
        "src": "暗闇の術:参",
        "dst": "暗黑之术:叁",
        "rm": "魔法"
    },
    {
        "src": "毒盛の術:壱",
        "dst": "毒盛之术:壹",
        "rm": "魔法"
    },
    {
        "src": "毒盛の術:弐",
        "dst": "毒盛之术:贰",
        "rm": "魔法"
    },
    {
        "src": "毒盛の術:参",
        "dst": "毒盛之术:叁",
        "rm": "魔法"
    },
    {
        "src": "遁甲の術:壱",
        "dst": "遁甲之术:壹",
        "rm": "魔法"
    },
    {
        "src": "遁甲の術:弐",
        "dst": "遁甲之术:贰",
        "rm": "魔法"
    },
    {
        "src": "セイレーン召喚",
        "dst": "塞壬召唤",
        "rm": "魔法"
    },
    {
        "src": "魔物のレクイエムII",
        "dst": "魔物的安魂曲II",
        "rm": "魔法"
    },
    {
        "src": "魔物のレクイエムIII",
        "dst": "魔物的安魂曲III",
        "rm": "魔法"
    },
    {
        "src": "魔物のレクイエムIV",
        "dst": "魔物的安魂曲IV",
        "rm": "魔法"
    },
    {
        "src": "魔物のレクイエムV",
        "dst": "魔物的安魂曲V",
        "rm": "魔法"
    },
    {
        "src": "魔物のレクイエムVI",
        "dst": "魔物的安魂曲VI",
        "rm": "魔法"
    },
    {
        "src": "魔物のレクイエムVII",
        "dst": "魔物的安魂曲VII",
        "rm": "魔法"
    },
    {
        "src": "魔物のレクイエムVIII",
        "dst": "魔物的安魂曲VIII",
        "rm": "魔法"
    },
    {
        "src": "魔物達のララバイ",
        "dst": "魔物的摇篮曲",
        "rm": "魔法"
    },
    {
        "src": "魔物達のララバイII",
        "dst": "魔物的摇篮曲II",
        "rm": "魔法"
    },
    {
        "src": "戦士達のピーアン",
        "dst": "战士的钢琴曲",
        "rm": "魔法"
    },
    {
        "src": "戦士達のピーアンII",
        "dst": "战士的钢琴曲II",
        "rm": "魔法"
    },
    {
        "src": "戦士達のピーアンIII",
        "dst": "战士的钢琴曲III",
        "rm": "魔法"
    },
    {
        "src": "戦士達のピーアンIV",
        "dst": "战士的钢琴曲IV",
        "rm": "魔法"
    },
    {
        "src": "戦士達のピーアンV",
        "dst": "战士的钢琴曲V",
        "rm": "魔法"
    },
    {
        "src": "戦士達のピーアンVI",
        "dst": "战士的钢琴曲VI",
        "rm": "魔法"
    },
    {
        "src": "戦士達のピーアンVII",
        "dst": "战士的钢琴曲VII",
        "rm": "魔法"
    },
    {
        "src": "戦士達のピーアンVIII",
        "dst": "战士的钢琴曲VIII",
        "rm": "魔法"
    },
    {
        "src": "魔道士のバラード",
        "dst": "魔道士的叙事谣",
        "rm": "魔法"
    },
    {
        "src": "魔道士のバラードII",
        "dst": "魔道士的叙事谣II",
        "rm": "魔法"
    },
    {
        "src": "魔道士のバラードIII",
        "dst": "魔道士的叙事谣III",
        "rm": "魔法"
    },
    {
        "src": "重装騎兵のミンネ",
        "dst": "重装骑兵的抒情恋歌",
        "rm": "魔法"
    },
    {
        "src": "重装騎兵のミンネII",
        "dst": "重装骑兵的抒情恋歌II",
        "rm": "魔法"
    },
    {
        "src": "重装騎兵のミンネIII",
        "dst": "重装骑兵的抒情恋歌III",
        "rm": "魔法"
    },
    {
        "src": "重装騎兵のミンネIV",
        "dst": "重装骑兵的抒情恋歌IV",
        "rm": "魔法"
    },
    {
        "src": "重装騎兵のミンネV",
        "dst": "重装骑兵的抒情恋歌V",
        "rm": "魔法"
    },
    {
        "src": "猛者のメヌエット",
        "dst": "猛者的小步舞曲",
        "rm": "魔法"
    },
    {
        "src": "猛者のメヌエットII",
        "dst": "猛者的小步舞曲II",
        "rm": "魔法"
    },
    {
        "src": "猛者のメヌエットIII",
        "dst": "猛者的小步舞曲III",
        "rm": "魔法"
    },
    {
        "src": "猛者のメヌエットIV",
        "dst": "猛者的小步舞曲IV",
        "rm": "魔法"
    },
    {
        "src": "猛者のメヌエットV",
        "dst": "猛者的小步舞曲V",
        "rm": "魔法"
    },
    {
        "src": "剣闘士のマドリガル",
        "dst": "剑斗士的牧歌",
        "rm": "魔法"
    },
    {
        "src": "剣豪のマドリガル",
        "dst": "剑豪的牧歌",
        "rm": "魔法"
    },
    {
        "src": "狩人のプレリュード",
        "dst": "猎人的前奏曲",
        "rm": "魔法"
    },
    {
        "src": "弓師のプレリュード",
        "dst": "弓师的前奏曲",
        "rm": "魔法"
    },
    {
        "src": "闘羊士のマンボ",
        "dst": "斗羊士的曼波",
        "rm": "魔法"
    },
    {
        "src": "闘龍士のマンボ",
        "dst": "斗龙士的曼波",
        "rm": "魔法"
    },
    {
        "src": "鶏のオーバード",
        "dst": "鸡的狂想曲",
        "rm": "魔法"
    },
    {
        "src": "薬草のパストラル",
        "dst": "药草的田园曲",
        "rm": "魔法"
    },
    {
        "src": "チョコボのハミング",
        "dst": "陆行鸟的哼唱",
        "rm": "魔法"
    },
    {
        "src": "光明のファンタジア",
        "dst": "光明幻想曲",
        "rm": "魔法"
    },
    {
        "src": "小話のオペレッタ",
        "dst": "小故事的轻歌剧",
        "rm": "魔法"
    },
    {
        "src": "腹話のオペレッタ",
        "dst": "腹语的轻歌剧",
        "rm": "魔法"
    },
    {
        "src": "道化のオペレッタ",
        "dst": "小丑的轻歌剧",
        "rm": "魔法"
    },
    {
        "src": "黄金のカプリチオ",
        "dst": "黄金随想曲",
        "rm": "魔法"
    },
    {
        "src": "献身のセレナーデ",
        "dst": "献身小夜曲",
        "rm": "魔法"
    },
    {
        "src": "破邪のロンド",
        "dst": "破邪回旋曲",
        "rm": "魔法"
    },
    {
        "src": "ゴブリンのガボット",
        "dst": "哥布林的加沃特舞曲",
        "rm": "魔法"
    },
    {
        "src": "サボテンダーフーガ",
        "dst": "仙人掌赋格曲",
        "rm": "魔法"
    },
    {
        "src": "栄典の戴冠マーチ",
        "dst": "荣典加冕进行曲",
        "rm": "魔法"
    },
    {
        "src": "冷静と情熱のアリア",
        "dst": "冷静与热情的咏叹调",
        "rm": "魔法"
    },
    {
        "src": "無敵の進撃マーチ",
        "dst": "无敌进军进行曲",
        "rm": "魔法"
    },
    {
        "src": "栄光の凱旋マーチ",
        "dst": "荣光凯旋进行曲",
        "rm": "魔法"
    },
    {
        "src": "戦場のエレジー",
        "dst": "战场挽歌",
        "rm": "魔法"
    },
    {
        "src": "修羅のエレジー",
        "dst": "修罗挽歌",
        "rm": "魔法"
    },
    {
        "src": "地獄のエレジー",
        "dst": "地狱挽歌",
        "rm": "魔法"
    },
    {
        "src": "剛力のエチュード",
        "dst": "刚力练习曲",
        "rm": "魔法"
    },
    {
        "src": "器用のエチュード",
        "dst": "灵巧练习曲",
        "rm": "魔法"
    },
    {
        "src": "元気のエチュード",
        "dst": "元气练习曲",
        "rm": "魔法"
    },
    {
        "src": "機敏のエチュード",
        "dst": "敏捷练习曲",
        "rm": "魔法"
    },
    {
        "src": "知恵のエチュード",
        "dst": "智慧练习曲",
        "rm": "魔法"
    },
    {
        "src": "精神のエチュード",
        "dst": "精神练习曲",
        "rm": "魔法"
    },
    {
        "src": "魅了のエチュード",
        "dst": "魅惑练习曲",
        "rm": "魔法"
    },
    {
        "src": "怪力のエチュード",
        "dst": "怪力练习曲",
        "rm": "魔法"
    },
    {
        "src": "妙技のエチュード",
        "dst": "妙技练习曲",
        "rm": "魔法"
    },
    {
        "src": "活力のエチュード",
        "dst": "活力练习曲",
        "rm": "魔法"
    },
    {
        "src": "俊敏のエチュード",
        "dst": "俊敏练习曲",
        "rm": "魔法"
    },
    {
        "src": "英知のエチュード",
        "dst": "英知练习曲",
        "rm": "魔法"
    },
    {
        "src": "理力のエチュード",
        "dst": "理力练习曲",
        "rm": "魔法"
    },
    {
        "src": "魅惑のエチュード",
        "dst": "魅惑练习曲",
        "rm": "魔法"
    },
    {
        "src": "耐火カロル第一楽章",
        "dst": "耐火颂歌第一乐章",
        "rm": "魔法"
    },
    {
        "src": "耐寒カロル第一楽章",
        "dst": "耐寒颂歌第一乐章",
        "rm": "魔法"
    },
    {
        "src": "耐風カロル第一楽章",
        "dst": "耐风颂歌第一乐章",
        "rm": "魔法"
    },
    {
        "src": "耐震カロル第一楽章",
        "dst": "耐震颂歌第一乐章",
        "rm": "魔法"
    },
    {
        "src": "耐電カロル第一楽章",
        "dst": "耐电颂歌第一乐章",
        "rm": "魔法"
    },
    {
        "src": "耐波カロル第一楽章",
        "dst": "耐波颂歌第一乐章",
        "rm": "魔法"
    },
    {
        "src": "耐光カロル第一楽章",
        "dst": "耐光颂歌第一乐章",
        "rm": "魔法"
    },
    {
        "src": "耐闇カロル第一楽章",
        "dst": "耐暗颂歌第一乐章",
        "rm": "魔法"
    },
    {
        "src": "耐火カロル第二楽章",
        "dst": "耐火颂歌第二乐章",
        "rm": "魔法"
    },
    {
        "src": "耐寒カロル第二楽章",
        "dst": "耐寒颂歌第二乐章",
        "rm": "魔法"
    },
    {
        "src": "耐風カロル第二楽章",
        "dst": "耐风颂歌第二乐章",
        "rm": "魔法"
    },
    {
        "src": "耐震カロル第二楽章",
        "dst": "耐震颂歌第二乐章",
        "rm": "魔法"
    },
    {
        "src": "耐電カロル第二楽章",
        "dst": "耐电颂歌第二乐章",
        "rm": "魔法"
    },
    {
        "src": "耐波カロル第二楽章",
        "dst": "耐波颂歌第二乐章",
        "rm": "魔法"
    },
    {
        "src": "耐光カロル第二楽章",
        "dst": "耐光颂歌第二乐章",
        "rm": "魔法"
    },
    {
        "src": "耐闇カロル第二楽章",
        "dst": "耐暗颂歌第二乐章",
        "rm": "魔法"
    },
    {
        "src": "炎のスレノディ",
        "dst": "炎之哀歌",
        "rm": "魔法"
    },
    {
        "src": "氷のスレノディ",
        "dst": "冰之哀歌",
        "rm": "魔法"
    },
    {
        "src": "風のスレノディ",
        "dst": "风之哀歌",
        "rm": "魔法"
    },
    {
        "src": "土のスレノディ",
        "dst": "土之哀歌",
        "rm": "魔法"
    },
    {
        "src": "雷のスレノディ",
        "dst": "雷之哀歌",
        "rm": "魔法"
    },
    {
        "src": "水のスレノディ",
        "dst": "水之哀歌",
        "rm": "魔法"
    },
    {
        "src": "光のスレノディ",
        "dst": "光之哀歌",
        "rm": "魔法"
    },
    {
        "src": "闇のスレノディ",
        "dst": "暗之哀歌",
        "rm": "魔法"
    },
    {
        "src": "魔法のフィナーレ",
        "dst": "魔法的最终乐章",
        "rm": "魔法"
    },
    {
        "src": "魔物のララバイ",
        "dst": "魔物的摇篮曲",
        "rm": "魔法"
    },
    {
        "src": "女神のヒムヌス",
        "dst": "女神赞歌",
        "rm": "魔法"
    },
    {
        "src": "チョコボのマズルカ",
        "dst": "陆行鸟玛祖卡",
        "rm": "魔法"
    },
    {
        "src": "乙女のヴィルレー",
        "dst": "少女的双韵短诗",
        "rm": "魔法"
    },
    {
        "src": "ラプトルのマズルカ",
        "dst": "盗龙玛祖卡",
        "rm": "魔法"
    },
    {
        "src": "魔物のシルベント",
        "dst": "魔物的服务歌",
        "rm": "魔法"
    },
    {
        "src": "冒険者のダージュ",
        "dst": "冒险者的葬歌",
        "rm": "魔法"
    },
    {
        "src": "警戒のスケルツォ",
        "dst": "警戒谐谑曲",
        "rm": "魔法"
    },
    {
        "src": "魔物のララバイII",
        "dst": "魔物摇篮曲II",
        "rm": "魔法"
    },
    {
        "src": "恋情のノクターン",
        "dst": "恋情夜曲",
        "rm": "魔法"
    },
    {
        "src": "月下の術:壱",
        "dst": "月下之术:壹",
        "rm": "魔法"
    },
    {
        "src": "夜陰の術:壱",
        "dst": "夜阴之术:壹",
        "rm": "魔法"
    },
    {
        "src": "妙手の術:壱",
        "dst": "妙手之术:壹",
        "rm": "魔法"
    },
    {
        "src": "幽林の術:壱",
        "dst": "幽林之术:壹",
        "rm": "魔法"
    },
    {
        "src": "活火の術:壱",
        "dst": "活火之术:壹",
        "rm": "魔法"
    },
    {
        "src": "身替の術:壱",
        "dst": "替身之术:壹",
        "rm": "魔法"
    },
    {
        "src": "カーバンクル",
        "dst": "宝石兽",
        "rm": "灵兽，彩虹之子"
    },
    {
        "src": "リヴァイアサン",
        "dst": "利维亚桑",
        "rm": "幻兽"
    },
    {
        "src": "シヴァ",
        "dst": "希瓦",
        "rm": "幻兽"
    },
    {
        "src": "フェニックス",
        "dst": "菲尼克斯",
        "rm": "灵兽，再生之鸟"
    },
    {
        "src": "ディアボロス",
        "dst": "迪亚波罗斯",
        "rm": "灵兽，梦之使者"
    },
    {
        "src": "フェンリル",
        "dst": "芬里尔",
        "rm": "灵兽，星月的指引"
    },
    {
        "src": "バハムート",
        "dst": "巴哈姆特",
        "rm": "灵兽，空之霸者"
    },
    {
        "src": "チャママ",
        "dst": "查玛玛",
        "rm": "人物，塔鲁塔鲁族"
    },
    {
        "src": "クッキー",
        "dst": "库奇",
        "rm": "人物，塔鲁塔鲁族"
    },
    {
        "src": "チェルキキ",
        "dst": "切露奇奇",
        "rm": "人物，塔鲁塔鲁族"
    },
    {
        "src": "マッキー",
        "dst": "马奇",
        "rm": "人物，塔鲁塔鲁族"
    },
    {
        "src": "カオス",
        "dst": "卡奥斯",
        "rm": "灵兽，蚀世之灾厄"
    },
    {
        "src": "カオス",
        "dst": "卡奥斯",
        "rm": "灵兽，蚀世之灾厄"
    },
    {
        "src": "デム",
        "dst": "德姆",
        "rm": "岩名。古国吉拉特的遗产结构，有德姆、梅亚、霍拉三所"
    },
    {
        "src": "メア",
        "dst": "梅亚",
        "rm": "岩名。古国吉拉特的遗产结构，有德姆、梅亚、霍拉三所"
    },
    {
        "src": "ホラ",
        "dst": "霍拉",
        "rm": "岩名。古国吉拉特的遗产结构，有德姆、梅亚、霍拉三所"
    },
    {
        "src": "クリスタルライン",
        "dst": "水晶线",
        "rm": "古国吉拉特的遗产结构，连接终端和多个母水晶以在之间传递能量"
    },
    {
        "src": "シグネット",
        "dst": "认印",
        "rm": "状态，征战的公认参与者所具有的状态"
    },
    {
        "src": "岩",
        "dst": "岩",
        "rm": "古国吉拉特的遗产结构，有德姆、梅亚、霍拉三所"
    }
]